Workbook

Sheet Inc5000_Business_Analysis.xlsx
A1: _input | B1: _num | C1: _widgetName | D1: _source | E1: _resultNumber | F1: _pageUrl | G1: id | H1: rank | I1: workers | J1: company | K1: url | L1: state_l | M1: state_s | N1: city | O1: metro | P1: growth | Q1: revenue | R1: industry | S1: yrs_on_list
B2: 1 | C2: Inc5000 Company List | D2: Inc5000 Company List | E2: 1 | F2: http://www.inc.com/inc5000list/json/inc5000_2014.json | G2: 22890 | H2: 1 | I2: 227 | J2: Fuhu | K2: fuhu | L2: California | M2: CA | N2: El Segundo | O2: Los Angeles | P2: 158956.91 | Q2: 195640000 | R2: Consumer Products & Services | S2: 2
B3: 2 | C3: Inc5000 Company List | D3: Inc5000 Company List | E3: 2 | F3: http://www.inc.com/inc5000list/json/inc5000_2014.json | G3: 25747 | H3: 2 | I3: 191 | J3: Quest Nutrition | K3: quest-nutrition | L3: California | M3: CA | N3: El Segundo | O3: Los Angeles | P3: 57347.925 | Q3: 82640563 | R3: Food & Beverage | S3: 1
B4: 3 | C4: Inc5000 Company List | D4: Inc5000 Company List | E4: 3 | F4: http://www.inc.com/inc5000list/json/inc5000_2014.json | G4: 25643 | H4: 3 | I4: 145 | J4: Reliant Asset Management | K4: reliant-asset-management | L4: Virginia | M4: VA | N4: Arlington | O4: Washington DC | P4: 55460.165 | Q4: 85076502 | R4: Business Products & Services | S4: 1
B5: 4 | C5: Inc5000 Company List | D5: Inc5000 Company List | E5: 4 | F5: http://www.inc.com/inc5000list/json/inc5000_2014.json | G5: 26098 | H5: 4 | I5: 62 | J5: Superfish | K5: superfish | L5: California | M5: CA | N5: Palo Alto | O5: San Jose | P5: 26042.963 | Q5: 35293000 | R5: Software | S5: 1
B6: 5 | C6: Inc5000 Company List | D6: Inc5000 Company List | E6: 5 | F6: http://www.inc.com/inc5000list/json/inc5000_2014.json | G6: 26182 | H6: 5 | I6: 92 | J6: Acacia Communications | K6: acacia-communications | L6: Massachusetts | M6: MA | N6: Maynard | O6: Boston | P6: 20690.458 | Q6: 77652360 | R6: Telecommunications | S6: 1
B7: 6 | C7: Inc5000 Company List | D7: Inc5000 Company List | E7: 6 | F7: http://www.inc.com/inc5000list/json/inc5000_2014.json | G7: 22913 | H7: 6 | I7: 50 | J7: Provider Power | K7: provider-power | L7: Maine | M7: ME | N7: Auburn | O7: Lewiston-Auburn ME | P7: 19876.517 | Q7: 137977203 | R7: Energy | S7: 2
B8: 7 | C8: Inc5000 Company List | D8: Inc5000 Company List | E8: 7 | F8: http://www.inc.com/inc5000list/json/inc5000_2014.json | G8: 22937 | H8: 7 | I8: 129 | J8: Crescendo Bioscience | K8: crescendo-bioscience | L8: California | M8: CA | N8: South San Francisco | O8: San Francisco | P8: 18375.069 | Q8: 27308000 | R8: Health | S8: 2
B9: 8 | C9: Inc5000 Company List | D9: Inc5000 Company List | E9: 8 | F9: http://www.inc.com/inc5000list/json/inc5000_2014.json | G9: 25413 | H9: 8 | I9: 130 | J9: Plexus Worldwide | K9: plexus-worldwide | L9: Arizona | M9: AZ | N9: Scottsdale | O9: Phoenix | P9: 16457.653 | Q9: 159897088 | R9: Health | S9: 1
B10: 9 | C10: Inc5000 Company List | D10: Inc5000 Company List | E10: 9 | F10: http://www.inc.com/inc5000list/json/inc5000_2014.json | G10: 26079 | H10: 9 | I10: 264 | J10: Vacasa | K10: vacasa | L10: Oregon | M10: OR | N10: Portland | O10: Portland OR | P10: 16192.061 | Q10: 26263454 | R10: Travel & Hospitality | S10: 1
B11: 10 | C11: Inc5000 Company List | D11: Inc5000 Company List | E11: 10 | F11: http://www.inc.com/inc5000list/json/inc5000_2014.json | G11: 25861 | H11: 10 | I11: 11 | J11: Go Energies | K11: go-energies | L11: North Carolina | M11: NC | N11: Wilmington | O11: Wilmington NC | P11: 16006.801 | Q11: 32851754 | R11: Energy | S11: 1
B12: 11 | C12: Inc5000 Company List | D12: Inc5000 Company List | E12: 11 | F12: http://www.inc.com/inc5000list/json/inc5000_2014.json | G12: 25231 | H12: 11 | I12: 113 | J12: Minute Key | K12: minute-key | L12: Colorado | M12: CO | N12: Boulder | O12: Boulder CO | P12: 14588.345 | Q12: 15782039 | R12: Consumer Products & Services | S12: 1
B13: 12 | C13: Inc5000 Company List | D13: Inc5000 Company List | E13: 12 | F13: http://www.inc.com/inc5000list/json/inc5000_2014.json | G13: 26450 | H13: 12 | I13: 135 | J13: Sainstore | K13: sainstore | L13: Kansas | M13: KS | N13: Lenexa | O13: Waterloo-Cedar Falls IA | P13: 14086.513 | Q13: 19243863 | R13: Business Products & Services | S13: 1
... B118: 117 | C118: Inc5000 Company List | D118: Inc5000 Company List | E118: 117 | F118: http://www.inc.com/inc5000list/json/inc5000_2014.json | G118: 25855 | H118: 117 | I118: 458 | J118: hCentive | K118: hcentive | L118: Virginia | M118: VA | N118: Reston | O118: Washington DC | P118: 3214.4606 | Q118: 26493445 | R118: Health | S118: 1
B119: 118 | C119: Inc5000 Company List | D119: Inc5000 Company List | E119: 118 | F119: http://www.inc.com/inc5000list/json/inc5000_2014.json | G119: 22903 | H119: 118 | I119: 14 | J119: Intelligent Audit | K119: intelligent-audit | L119: New Jersey | M119: NJ | N119: Rochelle Park | P119: 3122.0588 | Q119: 318842114 | R119: Logistics & Transportation | S119: 2
B120: 119 | C120: Inc5000 Company List | D120: Inc5000 Company List | E120: 119 | F120: http://www.inc.com/inc5000list/json/inc5000_2014.json | G120: 26332 | H120: 119 | I120: 60 | J120: SimpliSafe Home Security | K120: simplisafe-home-security | L120: Massachusetts | M120: MA | N120: Cambridge | O120: Boston | P120: 3075.8406 | Q120: 38454825 | R120: Security | S120: 1
B121: 120 | C121: Inc5000 Company List | D121: Inc5000 Company List | E121: 120 | F121: http://www.inc.com/inc5000list/json/inc5000_2014.json | G121: 25436 | H121: 120 | I121: 43 | J121: Boxman Studios | K121: boxman-studios | L121: North Carolina | M121: NC | N121: Charlotte | O121: Charlotte | P121: 3074.0826 | Q121: 4322910 | R121: Business Products & Services | S121: 1
B122: 121 | C122: Inc5000 Company List | D122: Inc5000 Company List | E122: 121 | F122: http://www.inc.com/inc5000list/json/inc5000_2014.json | G122: 26277 | H122: 121 | I122: 30 | J122: SeatGeek | K122: seatgeek | L122: New York | M122: NY | N122: New York | O122: New York City | P122: 3039.1304 | Q122: 12274000 | R122: Consumer Products & Services | S122: 1
B123: 122 | C123: Inc5000 Company List | D123: Inc5000 Company List | E123: 122 | F123: http://www.inc.com/inc5000list/json/inc5000_2014.json | G123: 24847 | H123: 122 | I123: 23 | J123: Smashwords | K123: smashwords | L123: California | M123: CA | N123: Los Gatos | O123: San Jose | P123: 3018.5723 | Q123: 22037828 | R123: Media | S123: 1
B124: 123 | C124: Inc5000 Company List | D124: Inc5000 Company List | E124: 123 | F124: http://www.inc.com/inc5000list/json/inc5000_2014.json | G124: 21756 | H124: 123 | I124: 18 | J124: Securityhunter | K124: securityhunter | L124: Maryland | M124: MD | N124: Baltimore | O124: Baltimore | P124: 2998.3413 | Q124: 35931650 | R124: Government Services | S124: 3
B125: 124 | C125: Inc5000 Company List | D125: Inc5000 Company List | E125: 124 | F125: http://www.inc.com/inc5000list/json/inc5000_2014.json | G125: 21024 | H125: 124 | I125: 74 | J125: VRx | K125: vrx | L125: Utah | M125: UT | N125: Salt Lake City | O125: Salt Lake City | P125: 2987.2957 | Q125: 89554237 | R125: Health | S125: 3
B126: 125 | C126: Inc5000 Company List | D126: Inc5000 Company List | E126: 125 | F126: http://www.inc.com/inc5000list/json/inc5000_2014.json | G126: 25425 | H126: 125 | I126: 42 | J126: SmackTom.com | K126: smacktomcom | L126: Florida | M126: FL | N126: Miami | O126: Miami | P126: 2963.7255 | Q126: 3125000 | R126: Retail | S126: 1
B127: 126 | C127: Inc5000 Company List | D127: Inc5000 Company List | E127: 126 | F127: http://www.inc.com/inc5000list/json/inc5000_2014.json | G127: 25034 | H127: 126 | I127: 10 | J127: Virtual Fleet Supervisor | K127: virtual-fleet-supervisor | L127: Florida | M127: FL | N127: Oviedo | O127: Orlando FL | P127: 2948.8362 | Q127: 3526101 | R127: Software | S127: 1
B128: 127 | C128: Inc5000 Company List | D128: Inc5000 Company List | E128: 127 | F128: http://www.inc.com/inc5000list/json/inc5000_2014.json | G128: 25283 | H128: 127 | I128: 262 | J128: CareCloud | K128: carecloud | L128: Florida | M128: FL | N128: Miami | O128: Miami | P128: 2939.6153 | Q128: 10455000 | R128: Health | S128: 1
B129: 128 | C129: Inc5000 Company List | D129: Inc5000 Company List | E129: 128 | F129: http://www.inc.com/inc5000list/json/inc5000_2014.json | G129: 24789 | H129: 128 | I129: 64 | J129: Fueled | K129: fueled | L129: New York | M129: NY | N129: New York | O129: New York City | P129: 2916.7442 | Q129: 6486000 | R129: Advertising & Marketing | S129: 1
B130: 129 | C130: Inc5000 Company List | D130: Inc5000 Company List | E130: 129 | F130: http://www.inc.com/inc5000list/json/inc5000_2014.json | G130: 26484 | H130: 129 | I130: 14 | J130: Bob's Watches | K130: bobs-watches | L130: California | M130: CA | N130: Westminster | O130: Los Angeles | P130: 2861.191 | Q130: 11101120 | R130: Retail | S130: 1
B131: 130 | C131: Inc5000 Company List | D131: Inc5000 Company List | E131: 130 | F131: http://www.inc.com/inc5000list/json/inc5000_2014.json | G131: 24852 | H131: 130 | I131: 6 | J131: CPA Trend | K131: cpa-trend | L131: New York | M131: NY | N131: Howard Beach | O131: New York City | P131: 2842.941 | Q131: 5826876 | R131: Advertising & Marketing | S131: 1
... B136: 135 | C136: Inc5000 Company List | D136: Inc5000 Company List | E136: 135 | F136: http://www.inc.com/inc5000list/json/inc5000_2014.json | G136: 23162 | H136: 135 | I136: 24 | J136: Marketsmith | K136: marketsmith | L136: New Jersey | M136: NJ | N136: Parsippany | O136: New York City | P136: 2752.5555 | Q136: 72908666 | R136: Advertising & Marketing | S136: 2
B137: 136 | C137: Inc5000 Company List | D137: Inc5000 Company List | E137: 136 | F137: http://www.inc.com/inc5000list/json/inc5000_2014.json | G137: 25279 | H137: 136 | I137: 18 | J137: Project Management Academy | K137: project-management-academy | L137: Indiana | M137: IN | N137: West Lafayette | P137: 2752.4901 | Q137: 8094996 | R137: Education | S137: 1
B138: 137 | C138: Inc5000 Company List | D138: Inc5000 Company List | E138: 137 | F138: http://www.inc.com/inc5000list/json/inc5000_2014.json | G138: 24932 | H138: 137 | I138: 25 | J138: Flying Cork Media | K138: flying-cork-media | L138: Pennsylvania | M138: PA | N138: Pittsburgh | O138: Pittsburgh PA | P138: 2745.4166 | Q138: 7502709 | R138: Advertising & Marketing | S138: 1
B139: 138 | C139: Inc5000 Company List | D139: Inc5000 Company List | E139: 138 | F139: http://www.inc.com/inc5000list/json/inc5000_2014.json | G139: 24888 | H139: 138 | I139: 160 | J139: Motivity Labs | K139: motivity-labs | L139: Texas | M139: TX | N139: Irving | O139: Dallas | P139: 2716.0018 | Q139: 3225899 | R139: IT Services | S139: 1
B140: 139 | C140: Inc5000 Company List | D140: Inc5000 Company List | E140: 139 | F140: http://www.inc.com/inc5000list/json/inc5000_2014.json | G140: 26263 | H140: 139 | I140: 232 | J140: Twilio | K140: twilio | L140: California | M140: CA | N140: San Francisco | O140: San Francisco | P140: 2710.8696 | Q140: 51720000 | R140: Telecommunications | S140: 1
B141: 140 | C141: Inc5000 Company List | D141: Inc5000 Company List | E141: 140 | F141: http://www.inc.com/inc5000list/json/inc5000_2014.json | G141: 25095 | H141: 140 | I141: 20 | J141: Signature Closers | K141: signature-closers | L141: Ohio | M141: OH | N141: Upper Arlington | O141: Columbus OH | P141: 2709.3881 | Q141: 3843580 | R141: Real Estate | S141: 1
B142: 141 | C142: Inc5000 Company List | D142: Inc5000 Company List | E142: 141 | F142: http://www.inc.com/inc5000list/json/inc5000_2014.json | G142: 25749 | H142: 141 | I142: 81 | J142: PureCars | K142: purecars | L142: South Carolina | M142: SC | N142: Charleston | O142: Charleston-North Charleston SC | P142: 2689.9672 | Q142: 8725985 | R142: Advertising & Marketing | S142: 1
B143: 142 | C143: Inc5000 Company List | D143: Inc5000 Company List | E143: 142 | F143: http://www.inc.com/inc5000list/json/inc5000_2014.json | G143: 25236 | H143: 142 | I143: 96 | J143: The Cambridge Institute of International Education | K143: the-cambridge-institute-of-international-education | L143: Massachusetts | M143: MA | N143: Waltham | O143: Boston | P143: 2683.3172 | Q143: 9784000 | R143: Education | S143: 1
B144: 143 | C144: Inc5000 Company List | D144: Inc5000 Company List | E144: 143 | F144: http://www.inc.com/inc5000list/json/inc5000_2014.json | G144: 25237 | H144: 143 | I144: 53 | J144: Market6 | K144: market6 | L144: Illinois | M144: IL | N144: Deerfield | O144: Chicago | P144: 2677.1957 | Q144: 15085838 | R144: Software | S144: 1
B145: 144 | C145: Inc5000 Company List | D145: Inc5000 Company List | E145: 144 | F145: http://www.inc.com/inc5000list/json/inc5000_2014.json | G145: 25594 | H145: 144 | I145: 53 | J145: LiveRamp | K145: liveramp | L145: California | M145: CA | N145: San Francisco | O145: San Francisco | P145: 2665.2479 | Q145: 21040412 | R145: Advertising & Marketing | S145: 1
B146: 145 | C146: Inc5000 Company List | D146: Inc5000 Company List | E146: 145 | F146: http://www.inc.com/inc5000list/json/inc5000_2014.json | G146: 25620 | H146: 145 | I146: 160 | J146: MyClean | K146: myclean | L146: New York | M146: NY | N146: New York | O146: New York City | P146: 2646.4033 | Q146: 4399793 | R146: Consumer Products & Services | S146: 1
B147: 146 | C147: Inc5000 Company List | D147: Inc5000 Company List | E147: 146 | F147: http://www.inc.com/inc5000list/json/inc5000_2014.json | G147: 26220 | H147: 146 | I147: 35 | J147: PresenceLearning | K147: presencelearning | L147: California | M147: CA | N147: San Francisco | O147: San Francisco | P147: 2634.2593 | Q147: 5906000 | R147: Education | S147: 1
B148: 147 | C148: Inc5000 Company List | D148: Inc5000 Company List | E148: 147 | F148: http://www.inc.com/inc5000list/json/inc5000_2014.json | G148: 26517 | H148: 147 | I148: 140 | J148: Residential Capital Management | K148: residential-capital-management | L148: Georgia | M148: GA | N148: Atlanta | O148: Atlanta | P148: 2626.018 | Q148: 30167124 | R148: Real Estate | S148: 1
B149: 148 | C149: Inc5000 Company List | D149: Inc5000 Company List | E149: 148 | F149: http://www.inc.com/inc5000list/json/inc5000_2014.json | G149: 25293 | H149: 148 | I149: 14 | J149: Total Technology Solutions Group | K149: total-technology-solutions-group | L149: Illinois | M149: IL | N149: St. Charles | O149: Chicago | P149: 2608.0908 | Q149: 3115496 | R149: Business Products & Services | S149: 1
... B163: 162 | C163: Inc5000 Company List | D163: Inc5000 Company List | E163: 162 | F163: http://www.inc.com/inc5000list/json/inc5000_2014.json | G163: 21880 | H163: 162 | I163: 24 | J163: ECHO Health | K163: echo-health | L163: Ohio | M163: OH | N163: Westlake | O163: Cleveland | P163: 2509.1757 | Q163: 46984261 | R163: Health | S163: 3
B164: 163 | C164: Inc5000 Company List | D164: Inc5000 Company List | E164: 163 | F164: http://www.inc.com/inc5000list/json/inc5000_2014.json | G164: 25153 | H164: 163 | I164: 75 | J164: Marathon TS | K164: marathon-ts | L164: Virginia | M164: VA | N164: Kilmarnock | P164: 2507.7517 | Q164: 6821409 | R164: Government Services | S164: 1
B165: 164 | C165: Inc5000 Company List | D165: Inc5000 Company List | E165: 164 | F165: http://www.inc.com/inc5000list/json/inc5000_2014.json | G165: 23033 | H165: 164 | I165: 8 | J165: AudioMicro | K165: audiomicro | L165: California | M165: CA | N165: Sherman Oaks | O165: Los Angeles | P165: 2495.6297 | Q165: 5426086 | R165: Media | S165: 2
B166: 165 | C166: Inc5000 Company List | D166: Inc5000 Company List | E166: 165 | F166: http://www.inc.com/inc5000list/json/inc5000_2014.json | G166: 25024 | H166: 165 | I166: 6 | J166: LED Supply | K166: led-supply | L166: Colorado | M166: CO | N166: Lakewood | O166: Denver | P166: 2474.0559 | Q166: 2877743 | R166: Business Products & Services | S166: 1
B167: 166 | C167: Inc5000 Company List | D167: Inc5000 Company List | E167: 166 | F167: http://www.inc.com/inc5000list/json/inc5000_2014.json | G167: 26487 | H167: 166 | I167: 6 | J167: LeGault Homes | K167: legault-homes | L167: Virginia | M167: VA | N167: Glen Allen | O167: Richmond VA | P167: 2455.075 | Q167: 7660396 | R167: Real Estate | S167: 1
B168: 167 | C168: Inc5000 Company List | D168: Inc5000 Company List | E168: 167 | F168: http://www.inc.com/inc5000list/json/inc5000_2014.json | G168: 25384 | H168: 167 | I168: 9 | J168: Forte International Tax | K168: forte-international-tax | L168: Illinois | M168: IL | N168: Evanston | O168: Chicago | P168: 2447.3722 | Q168: 3475711 | R168: Financial Services | S168: 1
B169: 168 | C169: Inc5000 Company List | D169: Inc5000 Company List | E169: 168 | F169: http://www.inc.com/inc5000list/json/inc5000_2014.json | G169: 25488 | H169: 168 | I169: 31 | J169: Paradigm Mechanical | K169: paradigm-mechanical | L169: California | M169: CA | N169: Lemon Grove | O169: San Diego | P169: 2439.5443 | Q169: 5250000 | R169: Construction | S169: 1
B170: 169 | C170: Inc5000 Company List | D170: Inc5000 Company List | E170: 169 | F170: http://www.inc.com/inc5000list/json/inc5000_2014.json | G170: 22992 | H170: 169 | I170: 45 | J170: Finance Store | K170: finance-store | L170: California | M170: CA | N170: Santa Ana | O170: Los Angeles | P170: 2436.3022 | Q170: 4590707 | R170: Financial Services | S170: 2
B171: 170 | C171: Inc5000 Company List | D171: Inc5000 Company List | E171: 170 | F171: http://www.inc.com/inc5000list/json/inc5000_2014.json | G171: 25512 | H171: 170 | I171: 27 | J171: Pure Incubation | K171: pure-incubation | L171: Massachusetts | M171: MA | N171: Topsfield | O171: Boston | P171: 2427.7792 | Q171: 4696917 | R171: Advertising & Marketing | S171: 1
B172: 171 | C172: Inc5000 Company List | D172: Inc5000 Company List | E172: 171 | F172: http://www.inc.com/inc5000list/json/inc5000_2014.json | G172: 25313 | H172: 171 | I172: 10 | J172: Kohana Coffee | K172: kohana-coffee | L172: Texas | M172: TX | N172: Austin | O172: Austin | P172: 2416.7762 | Q172: 2825786 | R172: Food & Beverage | S172: 1
B173: 172 | C173: Inc5000 Company List | D173: Inc5000 Company List | E173: 172 | F173: http://www.inc.com/inc5000list/json/inc5000_2014.json | G173: 26221 | H173: 172 | I173: 107 | J173: Ensighten | K173: ensighten | L173: California | M173: CA | N173: Cupertino | O173: San Jose | P173: 2415.8055 | Q173: 8277000 | R173: Advertising & Marketing | S173: 1
B174: 173 | C174: Inc5000 Company List | D174: Inc5000 Company List | E174: 173 | F174: http://www.inc.com/inc5000list/json/inc5000_2014.json | G174: 26167 | H174: 173 | I174: 123 | J174: Pathway Genomics | K174: pathway-genomics | L174: California | M174: CA | N174: San Diego | O174: San Diego | P174: 2415.5285 | Q174: 14426053 | R174: Health | S174: 1
B175: 174 | C175: Inc5000 Company List | D175: Inc5000 Company List | E175: 174 | F175: http://www.inc.com/inc5000list/json/inc5000_2014.json | G175: 24957 | H175: 174 | I175: 325 | J175: CenseoHealth | K175: censeohealth | L175: Texas | M175: TX | N175: Dallas | O175: Dallas | P175: 2406.9499 | Q175: 117230240 | R175: Health | S175: 1
B176: 175 | C176: Inc5000 Company List | D176: Inc5000 Company List | E176: 175 | F176: http://www.inc.com/inc5000list/json/inc5000_2014.json | G176: 26180 | H176: 175 | I176: 270 | J176: 3A/WorldWide | K176: 3aworldwide | L176: Florida | M176: FL | N176: Miami | O176: Miami | P176: 2402.7683 | Q176: 57568000 | R176: Advertising & Marketing | S176: 1
... B188: 187 | C188: Inc5000 Company List | D188: Inc5000 Company List | E188: 187 | F188: http://www.inc.com/inc5000list/json/inc5000_2014.json | G188: 25128 | H188: 187 | I188: 15 | J188: NITS Solutions | K188: nits-solutions | L188: Michigan | M188: MI | N188: Novi | O188: Detroit | P188: 2291.3176 | Q188: 2775411 | R188: IT Services | S188: 1
B189: 188 | C189: Inc5000 Company List | D189: Inc5000 Company List | E189: 188 | F189: http://www.inc.com/inc5000list/json/inc5000_2014.json | G189: 25869 | H189: 188 | I189: 18 | J189: Paramount Lodging Advisors | K189: paramount-lodging-advisors | L189: Illinois | M189: IL | N189: Chicago | P189: 2288.3653 | Q189: 2465605 | R189: Real Estate | S189: 1
B190: 189 | C190: Inc5000 Company List | D190: Inc5000 Company List | E190: 189 | F190: http://www.inc.com/inc5000list/json/inc5000_2014.json | G190: 25783 | H190: 189 | I190: 35 | J190: EmazingLights | K190: emazinglights | L190: California | M190: CA | N190: Anaheim | O190: Los Angeles | P190: 2281.335 | Q190: 5842010 | R190: Retail | S190: 1
B191: 190 | C191: Inc5000 Company List | D191: Inc5000 Company List | E191: 190 | F191: http://www.inc.com/inc5000list/json/inc5000_2014.json | G191: 26528 | H191: 190 | I191: 35 | J191: Level Interactive | K191: level-interactive | L191: Pennsylvania | M191: PA | N191: Pittsburgh | O191: Pittsburgh PA | P191: 2258.7014 | Q191: 11958616 | R191: Advertising & Marketing | S191: 1
B192: 191 | C192: Inc5000 Company List | D192: Inc5000 Company List | E192: 191 | F192: http://www.inc.com/inc5000list/json/inc5000_2014.json | G192: 26255 | H192: 191 | I192: 75 | J192: shopkick | K192: shopkick | L192: California | M192: CA | N192: Redwood City | O192: San Francisco | P192: 2250.0409 | Q192: 26319118 | R192: Retail | S192: 1
B193: 192 | C193: Inc5000 Company List | D193: Inc5000 Company List | E193: 192 | F193: http://www.inc.com/inc5000list/json/inc5000_2014.json | G193: 25486 | H193: 192 | I193: 129 | J193: TekWissen | K193: tekwissen | L193: Michigan | M193: MI | N193: Ann Arbor | O193: Ann Arbor MI | P193: 2236.1753 | Q193: 7802802 | R193: IT Services | S193: 1
B194: 193 | C194: Inc5000 Company List | D194: Inc5000 Company List | E194: 193 | F194: http://www.inc.com/inc5000list/json/inc5000_2014.json | G194: 25501 | H194: 193 | I194: 15 | J194: VPCinnovations | K194: vpcinnovations | L194: Wisconsin | M194: WI | N194: Mount Pleasant | O194: Chicago | P194: 2234.3619 | Q194: 5390952 | R194: Computer Hardware | S194: 1
B195: 194 | C195: Inc5000 Company List | D195: Inc5000 Company List | E195: 194 | F195: http://www.inc.com/inc5000list/json/inc5000_2014.json | G195: 25433 | H195: 194 | I195: 42 | J195: Clean Energy Collective | K195: clean-energy-collective | L195: Colorado | M195: CO | N195: Boulder | O195: Boulder CO | P195: 2216.9118 | Q195: 9453000 | R195: Energy | S195: 1
B196: 195 | C196: Inc5000 Company List | D196: Inc5000 Company List | E196: 195 | F196: http://www.inc.com/inc5000list/json/inc5000_2014.json | G196: 26030 | H196: 195 | I196: 13 | J196: Silver Bullet Construction | K196: silver-bullet-construction | L196: Texas | M196: TX | N196: Dalworthington Garden | O196: Dallas | P196: 2215.5963 | Q196: 2524000 | R196: Construction | S196: 1
B197: 196 | C197: Inc5000 Company List | D197: Inc5000 Company List | E197: 196 | F197: http://www.inc.com/inc5000list/json/inc5000_2014.json | G197: 26326 | H197: 196 | I197: 48 | J197: Aegis Corps | K197: aegis-corps | L197: Virginia | M197: VA | N197: Chantilly | O197: Washington DC | P197: 2208.3868 | Q197: 2900488 | R197: Government Services | S197: 1
B198: 197 | C198: Inc5000 Company List | D198: Inc5000 Company List | E198: 197 | F198: http://www.inc.com/inc5000list/json/inc5000_2014.json | G198: 22899 | H198: 197 | I198: 300 | J198: uBreakiFix | K198: ubreakifix | L198: Florida | M198: FL | N198: Orlando | O198: Orlando FL | P198: 2188.8349 | Q198: 26472870 | R198: Retail | S198: 2
B199: 198 | C199: Inc5000 Company List | D199: Inc5000 Company List | E199: 198 | F199: http://www.inc.com/inc5000list/json/inc5000_2014.json | G199: 25037 | H199: 198 | I199: 302 | J199: Culture.Service.Growth. | K199: cultureservicegrowth | L199: Texas | M199: TX | N199: San Antonio | O199: San Antonio TX | P199: 2182.0898 | Q199: 7993065 | R199: Business Products & Services | S199: 1
B200: 199 | C200: Inc5000 Company List | D200: Inc5000 Company List | E200: 199 | F200: http://www.inc.com/inc5000list/json/inc5000_2014.json | G200: 21023 | H200: 199 | I200: 72 | J200: CardCash.com | K200: cardcashcom | L200: New Jersey | M200: NJ | N200: Brick | O200: New York City | P200: 2181.7178 | Q200: 55788000 | R200: Consumer Products & Services | S200: 3
B201: 200 | C201: Inc5000 Company List | D201: Inc5000 Company List | E201: 200 | F201: http://www.inc.com/inc5000list/json/inc5000_2014.json | G201: 26083 | H201: 200 | I201: 450 | J201: Protein Bar | K201: protein-bar | L201: Illinois | M201: IL | N201: Chicago | O201: Chicago | P201: 2181.6917 | Q201: 14211083 | R201: Food & Beverage | S201: 1
... B268: 267 | C268: Inc5000 Company List | D268: Inc5000 Company List | E268: 267 | F268: http://www.inc.com/inc5000list/json/inc5000_2014.json | G268: 25674 | H268: 267 | I268: 142 | J268: Human Movement Management | K268: human-movement-management | L268: Colorado | M268: CO | N268: Louisville | O268: Boulder CO | P268: 1724.3576 | Q268: 9054816 | R268: Consumer Products & Services | S268: 1
B269: 268 | C269: Inc5000 Company List | D269: Inc5000 Company List | E269: 268 | F269: http://www.inc.com/inc5000list/json/inc5000_2014.json | G269: 25622 | H269: 268 | I269: 47 | J269: Allegheny Science & Technology | K269: allegheny-science-technology | L269: West Virginia | M269: WV | N269: Bridgeport | P269: 1723.2877 | Q269: 7023359 | R269: Government Services | S269: 1
B270: 269 | C270: Inc5000 Company List | D270: Inc5000 Company List | E270: 269 | F270: http://www.inc.com/inc5000list/json/inc5000_2014.json | G270: 22994 | H270: 269 | I270: 110 | J270: Hudl | K270: hudl | L270: Nebraska | M270: NE | N270: Lincoln | O270: Lincoln NE | P270: 1707.5863 | Q270: 22326800 | R270: Software | S270: 2
B271: 270 | C271: Inc5000 Company List | D271: Inc5000 Company List | E271: 270 | F271: http://www.inc.com/inc5000list/json/inc5000_2014.json | G271: 25092 | H271: 270 | I271: 69 | J271: GuideSpark | K271: guidespark | L271: California | M271: CA | N271: Menlo Park | O271: San Francisco | P271: 1703.5556 | Q271: 4058000 | R271: Software | S271: 1
B272: 271 | C272: Inc5000 Company List | D272: Inc5000 Company List | E272: 271 | F272: http://www.inc.com/inc5000list/json/inc5000_2014.json | G272: 25160 | H272: 271 | I272: 25 | J272: Optimus Technology | K272: optimus-technology | L272: Maryland | M272: MD | N272: Columbia | O272: Baltimore | P272: 1701.5569 | Q272: 2086383 | R272: IT Services | S272: 1
B273: 272 | C273: Inc5000 Company List | D273: Inc5000 Company List | E273: 272 | F273: http://www.inc.com/inc5000list/json/inc5000_2014.json | G273: 26438 | H273: 272 | I273: 22 | J273: Luxe Royale | K273: luxe-royale | L273: Nevada | M273: NV | N273: Las Vegas | O273: Las Vegas-Paradise NV | P273: 1696.071 | Q273: 2265115 | R273: Travel & Hospitality | S273: 1
B274: 273 | C274: Inc5000 Company List | D274: Inc5000 Company List | E274: 273 | F274: http://www.inc.com/inc5000list/json/inc5000_2014.json | G274: 24928 | H274: 273 | I274: 8 | J274: SoluComp | K274: solucomp | L274: Illinois | M274: IL | N274: South Barrington | O274: Chicago | P274: 1694.0032 | Q274: 2213172 | R274: Telecommunications | S274: 1
B275: 274 | C275: Inc5000 Company List | D275: Inc5000 Company List | E275: 274 | F275: http://www.inc.com/inc5000list/json/inc5000_2014.json | G275: 24922 | H275: 274 | I275: 15 | J275: RPM Freight Systems | K275: rpm-freight-systems | L275: Michigan | M275: MI | N275: Royal Oak | O275: Detroit | P275: 1683.3663 | Q275: 4647952 | R275: Logistics & Transportation | S275: 1
B276: 275 | C276: Inc5000 Company List | D276: Inc5000 Company List | E276: 275 | F276: http://www.inc.com/inc5000list/json/inc5000_2014.json | G276: 25684 | H276: 275 | I276: 24 | J276: Motivational Press | K276: motivational-press | L276: California | M276: CA | N276: Carlsbad | O276: San Diego | P276: 1675 | Q276: 2343000 | R276: Media | S276: 1
B277: 276 | C277: Inc5000 Company List | D277: Inc5000 Company List | E277: 276 | F277: http://www.inc.com/inc5000list/json/inc5000_2014.json | G277: 25951 | H277: 276 | I277: 41 | J277: Accordant Media | K277: accordant-media | L277: New York | M277: NY | N277: New York | O277: New York City | P277: 1663.0114 | Q277: 27119347 | R277: Advertising & Marketing | S277: 1
B278: 277 | C278: Inc5000 Company List | D278: Inc5000 Company List | E278: 277 | F278: http://www.inc.com/inc5000list/json/inc5000_2014.json | G278: 23059 | H278: 277 | I278: 100 | J278: iQuanti | K278: iquanti | L278: New Jersey | M278: NJ | N278: Hoboken | O278: New York City | P278: 1654.4182 | Q278: 5001355 | R278: Advertising & Marketing | S278: 2
B279: 278 | C279: Inc5000 Company List | D279: Inc5000 Company List | E279: 278 | F279: http://www.inc.com/inc5000list/json/inc5000_2014.json | G279: 26075 | H279: 278 | I279: 268 | J279: Bareburger | K279: bareburger | L279: New York | M279: NY | N279: Long Island City | O279: New York City | P279: 1652.3627 | Q279: 31150000 | R279: Food & Beverage | S279: 1
B280: 279 | C280: Inc5000 Company List | D280: Inc5000 Company List | E280: 279 | F280: http://www.inc.com/inc5000list/json/inc5000_2014.json | G280: 22972 | H280: 279 | I280: 74 | J280: BMA | K280: bma | L280: Kansas | M280: KS | N280: Leavenworth | O280: Kansas City MO-KS | P280: 1651.8539 | Q280: 14580032 | R280: Government Services | S280: 2
B281: 280 | C281: Inc5000 Company List | D281: Inc5000 Company List | E281: 280 | F281: http://www.inc.com/inc5000list/json/inc5000_2014.json | G281: 22959 | H281: 280 | I281: 73 | J281: CoverMyMeds | K281: covermymeds | L281: Ohio | M281: OH | N281: Twinsburg | O281: Akron OH | P281: 1647.939 | Q281: 18691673 | R281: Health | S281: 2
... B297: 296 | C297: Inc5000 Company List | D297: Inc5000 Company List | E297: 296 | F297: http://www.inc.com/inc5000list/json/inc5000_2014.json | G297: 26314 | H297: 296 | I297: 2 | J297: AcquisitionsAndRenewals.com | K297: acquisitionsandrenewalscom | L297: Nevada | M297: NV | N297: Henderson | O297: Las Vegas-Paradise NV | P297: 1548.8424 | Q297: 4628284 | R297: Telecommunications | S297: 1
B298: 297 | C298: Inc5000 Company List | D298: Inc5000 Company List | E298: 297 | F298: http://www.inc.com/inc5000list/json/inc5000_2014.json | G298: 22947 | H298: 297 | I298: 19 | J298: Bio Soil Enhancers | K298: bio-soil-enhancers | L298: Mississippi | M298: MS | N298: Hattiesburg | P298: 1538.9036 | Q298: 7811162 | R298: Manufacturing | S298: 2
B299: 298 | C299: Inc5000 Company List | D299: Inc5000 Company List | E299: 298 | F299: http://www.inc.com/inc5000list/json/inc5000_2014.json | G299: 26256 | H299: 298 | I299: 23 | J299: Cogito | K299: cogito | L299: Massachusetts | M299: MA | N299: Boston | O299: Boston | P299: 1528.9871 | Q299: 2524930 | R299: Software | S299: 1
B300: 299 | C300: Inc5000 Company List | D300: Inc5000 Company List | E300: 299 | F300: http://www.inc.com/inc5000list/json/inc5000_2014.json | G300: 26250 | H300: 299 | I300: 35 | J300: MorrisCore | K300: morriscore | L300: Florida | M300: FL | N300: Pompano Beach | O300: Miami | P300: 1520.2761 | Q300: 2064653 | R300: Advertising & Marketing | S300: 1
B301: 300 | C301: Inc5000 Company List | D301: Inc5000 Company List | E301: 300 | F301: http://www.inc.com/inc5000list/json/inc5000_2014.json | G301: 24920 | H301: 300 | I301: 7 | J301: Noi Solutions | K301: noi-solutions | L301: New York | M301: NY | N301: New York | O301: New York City | P301: 1519.4793 | Q301: 22833994 | R301: Business Products & Services | S301: 1
B302: 301 | C302: Inc5000 Company List | D302: Inc5000 Company List | E302: 301 | F302: http://www.inc.com/inc5000list/json/inc5000_2014.json | G302: 25993 | H302: 301 | I302: 32 | J302: KeVita Sparkling Probiotic Drinks | K302: kevita-sparkling-probiotic-drinks | L302: California | M302: CA | N302: Oxnard | O302: Oxnard-Thousand Oaks-Ventura CA | P302: 1518.5507 | Q302: 11168000 | R302: Food & Beverage | S302: 1
B303: 302 | C303: Inc5000 Company List | D303: Inc5000 Company List | E303: 302 | F303: http://www.inc.com/inc5000list/json/inc5000_2014.json | G303: 25740 | H303: 302 | I303: 12 | J303: HoverCam | K303: hovercam | L303: California | M303: CA | N303: San Diego | O303: San Diego | P303: 1517.0231 | Q303: 4760241 | R303: Manufacturing | S303: 1
B304: 303 | C304: Inc5000 Company List | D304: Inc5000 Company List | E304: 303 | F304: http://www.inc.com/inc5000list/json/inc5000_2014.json | G304: 21205 | H304: 303 | I304: 10 | J304: Apex Resources | K304: apex-resources | L304: Texas | M304: TX | N304: Dallas | O304: Dallas | P304: 1515.4893 | Q304: 25450095 | R304: Manufacturing | S304: 3
B305: 304 | C305: Inc5000 Company List | D305: Inc5000 Company List | E305: 304 | F305: http://www.inc.com/inc5000list/json/inc5000_2014.json | G305: 25708 | H305: 304 | I305: 25 | J305: SiteCompli | K305: sitecompli | L305: New York | M305: NY | N305: New York | O305: New York City | P305: 1512.312 | Q305: 5126072 | R305: Software | S305: 1
B306: 305 | C306: Inc5000 Company List | D306: Inc5000 Company List | E306: 305 | F306: http://www.inc.com/inc5000list/json/inc5000_2014.json | G306: 21597 | H306: 305 | I306: 80 | J306: Clearleap | K306: clearleap | L306: Georgia | M306: GA | N306: Duluth | O306: Atlanta | P306: 1509.6721 | Q306: 9819000 | R306: Software | S306: 3
B307: 306 | C307: Inc5000 Company List | D307: Inc5000 Company List | E307: 306 | F307: http://www.inc.com/inc5000list/json/inc5000_2014.json | G307: 22988 | H307: 306 | I307: 15 | J307: StartFinder | K307: startfinder | L307: Maryland | M307: MD | N307: Rockville | O307: Washington DC | P307: 1509.4059 | Q307: 3251000 | R307: Human Resources | S307: 2
B308: 307 | C308: Inc5000 Company List | D308: Inc5000 Company List | E308: 307 | F308: http://www.inc.com/inc5000list/json/inc5000_2014.json | G308: 21314 | H308: 307 | I308: 703 | J308: LongView International Technology Solutions | K308: longview-international-technology-solutions | L308: Virginia | M308: VA | N308: Alexandria | O308: Washington DC | P308: 1505.6112 | Q308: 128269211 | R308: Government Services | S308: 2
B309: 308 | C309: Inc5000 Company List | D309: Inc5000 Company List | E309: 308 | F309: http://www.inc.com/inc5000list/json/inc5000_2014.json | G309: 25239 | H309: 308 | I309: 188 | J309: Softhq | K309: softhq | L309: California | M309: CA | N309: San Diego | O309: San Diego | P309: 1496.7527 | Q309: 16058111 | R309: IT Services | S309: 1
B310: 309 | C310: Inc5000 Company List | D310: Inc5000 Company List | E310: 309 | F310: http://www.inc.com/inc5000list/json/inc5000_2014.json | G310: 25732 | H310: 309 | I310: 24 | J310: EveryMundo | K310: everymundo | L310: Florida | M310: FL | N310: Miami | O310: Miami | P310: 1495.2936 | Q310: 2454423 | R310: Advertising & Marketing | S310: 1
... B702: 701 | C702: Inc5000 Company List | D702: Inc5000 Company List | E702: 701 | F702: http://www.inc.com/inc5000list/json/inc5000_2014.json | G702: 23173 | H702: 701 | I702: 22 | J702: Caneel Group | K702: caneel-group | L702: New Jersey | M702: NJ | N702: Gibbsboro | O702: Philadelphia | P702: 645.4948 | Q702: 6225075 | R702: Financial Services | S702: 2
B703: 702 | C703: Inc5000 Company List | D703: Inc5000 Company List | E703: 702 | F703: http://www.inc.com/inc5000list/json/inc5000_2014.json | G703: 21342 | H703: 702 | I703: 70 | J703: Wellness Corporate Solutions | K703: wellness-corporate-solutions | L703: Maryland | M703: MD | N703: Bethesda | P703: 643.7388 | Q703: 12645835 | R703: Health | S703: 3
B704: 703 | C704: Inc5000 Company List | D704: Inc5000 Company List | E704: 703 | F704: http://www.inc.com/inc5000list/json/inc5000_2014.json | G704: 26365 | H704: 703 | I704: 26 | J704: Ready Set Rocket | K704: ready-set-rocket | L704: New York | M704: NY | N704: New York | O704: New York City | P704: 643.7046 | Q704: 3071500 | R704: Advertising & Marketing | S704: 1
...

Sheet Clean Data
A1: _num | B1: _widgetName | C1: _source | D1: _resultNumber | E1: _pageUrl | F1: id | G1: rank | H1: workers | I1: Company Size | J1: company | K1: url | L1: state_l | M1: state_s | N1: city | O1: metro | P1: growth | Q1: revenue | R1: industry | S1: yrs_on_list
A2: 1 | B2: Inc5000 Company List | C2: Inc5000 Company List | D2: 1 | E2: http://www.inc.com/inc5000list/json/inc5000_2014.json | F2: 22890 | G2: 1 | H2: 227 | I2: =IF(H2<=50,"Small",IF(H2<=200,"Medium",IF(H2<=500,"Large","Enterprise"))) -> Large | J2: Fuhu | K2: fuhu | L2: California | M2: CA | N2: El Segundo | O2: Los Angeles | P2: 158956.91 | Q2: 195640000 | R2: Consumer Products & Services | S2: 2
A3: 2 | B3: Inc5000 Company List | C3: Inc5000 Company List | D3: 2 | E3: http://www.inc.com/inc5000list/json/inc5000_2014.json | F3: 25747 | G3: 2 | H3: 191 | I3: =IF(H3<=50,"Small",IF(H3<=200,"Medium",IF(H3<=500,"Large","Enterprise"))) -> Medium | J3: Quest Nutrition | K3: quest-nutrition | L3: California | M3: CA | N3: El Segundo | O3: Los Angeles | P3: 57347.925 | Q3: 82640563 | R3: Food & Beverage | S3: 1
A4: 3 | B4: Inc5000 Company List | C4: Inc5000 Company List | D4: 3 | E4: http://www.inc.com/inc5000list/json/inc5000_2014.json | F4: 25643 | G4: 3 | H4: 145 | I4: =IF(H4<=50,"Small",IF(H4<=200,"Medium",IF(H4<=500,"Large","Enterprise"))) -> Medium | J4: Reliant Asset Management | K4: reliant-asset-management | L4: Virginia | M4: VA | N4: Arlington | O4: Washington DC | P4: 55460.165 | Q4: 85076502 | R4: Business Products & Services | S4: 1
A5: 4 | B5: Inc5000 Company List | C5: Inc5000 Company List | D5: 4 | E5: http://www.inc.com/inc5000list/json/inc5000_2014.json | F5: 26098 | G5: 4 | H5: 62 | I5: =IF(H5<=50,"Small",IF(H5<=200,"Medium",IF(H5<=500,"Large","Enterprise"))) -> Medium | J5: Superfish | K5: superfish | L5: California | M5: CA | N5: Palo Alto | O5: San Jose | P5: 26042.963 | Q5: 35293000 | R5: Software | S5: 1
A6: 5 | B6: Inc5000 Company List | C6: Inc5000 Company List | D6: 5 | E6: http://www.inc.com/inc5000list/json/inc5000_2014.json | F6: 26182 | G6: 5 | H6: 92 | I6: =IF(H6<=50,"Small",IF(H6<=200,"Medium",IF(H6<=500,"Large","Enterprise"))) -> Medium | J6: Acacia Communications | K6: acacia-communications | L6: Massachusetts | M6: MA | N6: Maynard | O6: Boston | P6: 20690.458 | Q6: 77652360 | R6: Telecommunications | S6: 1
A7: 6 | B7: Inc5000 Company List | C7: Inc5000 Company List | D7: 6 | E7: http://www.inc.com/inc5000list/json/inc5000_2014.json | F7: 22913 | G7: 6 | H7: 50 | I7: =IF(H7<=50,"Small",IF(H7<=200,"Medium",IF(H7<=500,"Large","Enterprise"))) -> Small | J7: Provider Power | K7: provider-power | L7: Maine | M7: ME | N7: Auburn | O7: Lewiston-Auburn ME | P7: 19876.517 | Q7: 137977203 | R7: Energy | S7: 2
A8: 7 | B8: Inc5000 Company List | C8: Inc5000 Company List | D8: 7 | E8: http://www.inc.com/inc5000list/json/inc5000_2014.json | F8: 22937 | G8: 7 | H8: 129 | I8: =IF(H8<=50,"Small",IF(H8<=200,"Medium",IF(H8<=500,"Large","Enterprise"))) -> Medium | J8: Crescendo Bioscience | K8: crescendo-bioscience | L8: California | M8: CA | N8: South San Francisco | O8: San Francisco | P8: 18375.069 | Q8: 27308000 | R8: Health | S8: 2
A9: 8 | B9: Inc5000 Company List | C9: Inc5000 Company List | D9: 8 | E9: http://www.inc.com/inc5000list/json/inc5000_2014.json | F9: 25413 | G9: 8 | H9: 130 | I9: =IF(H9<=50,"Small",IF(H9<=200,"Medium",IF(H9<=500,"Large","Enterprise"))) -> Medium | J9: Plexus Worldwide | K9: plexus-worldwide | L9: Arizona | M9: AZ | N9: Scottsdale | O9: Phoenix | P9: 16457.653 | Q9: 159897088 | R9: Health | S9: 1
A10: 9 | B10: Inc5000 Company List | C10: Inc5000 Company List | D10: 9 | E10: http://www.inc.com/inc5000list/json/inc5000_2014.json | F10: 26079 | G10: 9 | H10: 264 | I10: =IF(H10<=50,"Small",IF(H10<=200,"Medium",IF(H10<=500,"Large","Enterprise"))) -> Large | J10: Vacasa | K10: vacasa | L10: Oregon | M10: OR | N10: Portland | O10: Portland OR | P10: 16192.061 | Q10: 26263454 | R10: Travel & Hospitality | S10: 1
A11: 10 | B11: Inc5000 Company List | C11: Inc5000 Company List | D11: 10 | E11: http://www.inc.com/inc5000list/json/inc5000_2014.json | F11: 25861 | G11: 10 | H11: 11 | I11: =IF(H11<=50,"Small",IF(H11<=200,"Medium",IF(H11<=500,"Large","Enterprise"))) -> Small | J11: Go Energies | K11: go-energies | L11: North Carolina | M11: NC | N11: Wilmington | O11: Wilmington NC | P11: 16006.801 | Q11: 32851754 | R11: Energy | S11: 1
A12: 11 | B12: Inc5000 Company List | C12: Inc5000 Company List | D12: 11 | E12: http://www.inc.com/inc5000list/json/inc5000_2014.json | F12: 25231 | G12: 11 | H12: 113 | I12: =IF(H12<=50,"Small",IF(H12<=200,"Medium",IF(H12<=500,"Large","Enterprise"))) -> Medium | J12: Minute Key | K12: minute-key | L12: Colorado | M12: CO | N12: Boulder | O12: Boulder CO | P12: 14588.345 | Q12: 15782039 | R12: Consumer Products & Services | S12: 1
A13: 12 | B13: Inc5000 Company List | C13: Inc5000 Company List | D13: 12 | E13: http://www.inc.com/inc5000list/json/inc5000_2014.json | F13: 26450 | G13: 12 | H13: 135 | I13: =IF(H13<=50,"Small",IF(H13<=200,"Medium",IF(H13<=500,"Large","Enterprise"))) -> Medium | J13: Sainstore | K13: sainstore | L13: Kansas | M13: KS | N13: Lenexa | O13: Waterloo-Cedar Falls IA | P13: 14086.513 | Q13: 19243863 | R13: Business Products & Services | S13: 1
... A118: 117 | B118: Inc5000 Company List | C118: Inc5000 Company List | D118: 117 | E118: http://www.inc.com/inc5000list/json/inc5000_2014.json | F118: 25855 | G118: 117 | H118: 458 | I118: =IF(H118<=50,"Small",IF(H118<=200,"Medium",IF(H118<=500,"Large","Enterprise"))) -> Large | J118: hCentive | K118: hcentive | L118: Virginia | M118: VA | N118: Reston | O118: Washington DC | P118: 3214.4606 | Q118: 26493445 | R118: Health | S118: 1
A119: 118 | B119: Inc5000 Company List | C119: Inc5000 Company List | D119: 118 | E119: http://www.inc.com/inc5000list/json/inc5000_2014.json | F119: 22903 | G119: 118 | H119: 14 | I119: =IF(H119<=50,"Small",IF(H119<=200,"Medium",IF(H119<=500,"Large","Enterprise"))) -> Small | J119: Intelligent Audit | K119: intelligent-audit | L119: New Jersey | M119: NJ | N119: Rochelle Park | P119: 3122.0588 | Q119: 318842114 | R119: Logistics & Transportation | S119: 2
A120: 119 | B120: Inc5000 Company List | C120: Inc5000 Company List | D120: 119 | E120: http://www.inc.com/inc5000list/json/inc5000_2014.json | F120: 26332 | G120: 119 | H120: 60 | I120: =IF(H120<=50,"Small",IF(H120<=200,"Medium",IF(H120<=500,"Large","Enterprise"))) -> Medium | J120: SimpliSafe Home Security | K120: simplisafe-home-security | L120: Massachusetts | M120: MA | N120: Cambridge | O120: Boston | P120: 3075.8406 | Q120: 38454825 | R120: Security | S120: 1
A121: 120 | B121: Inc5000 Company List | C121: Inc5000 Company List | D121: 120 | E121: http://www.inc.com/inc5000list/json/inc5000_2014.json | F121: 25436 | G121: 120 | H121: 43 | I121: =IF(H121<=50,"Small",IF(H121<=200,"Medium",IF(H121<=500,"Large","Enterprise"))) -> Small | J121: Boxman Studios | K121: boxman-studios | L121: North Carolina | M121: NC | N121: Charlotte | O121: Charlotte | P121: 3074.0826 | Q121: 4322910 | R121: Business Products & Services | S121: 1
A122: 121 | B122: Inc5000 Company List | C122: Inc5000 Company List | D122: 121 | E122: http://www.inc.com/inc5000list/json/inc5000_2014.json | F122: 26277 | G122: 121 | H122: 30 | I122: =IF(H122<=50,"Small",IF(H122<=200,"Medium",IF(H122<=500,"Large","Enterprise"))) -> Small | J122: SeatGeek | K122: seatgeek | L122: New York | M122: NY | N122: New York | O122: New York City | P122: 3039.1304 | Q122: 12274000 | R122: Consumer Products & Services | S122: 1
A123: 122 | B123: Inc5000 Company List | C123: Inc5000 Company List | D123: 122 | E123: http://www.inc.com/inc5000list/json/inc5000_2014.json | F123: 24847 | G123: 122 | H123: 23 | I123: =IF(H123<=50,"Small",IF(H123<=200,"Medium",IF(H123<=500,"Large","Enterprise"))) -> Small | J123: Smashwords | K123: smashwords | L123: California | M123: CA | N123: Los Gatos | O123: San Jose | P123: 3018.5723 | Q123: 22037828 | R123: Media | S123: 1
A124: 123 | B124: Inc5000 Company List | C124: Inc5000 Company List | D124: 123 | E124: http://www.inc.com/inc5000list/json/inc5000_2014.json | F124: 21756 | G124: 123 | H124: 18 | I124: =IF(H124<=50,"Small",IF(H124<=200,"Medium",IF(H124<=500,"Large","Enterprise"))) -> Small | J124: Securityhunter | K124: securityhunter | L124: Maryland | M124: MD | N124: Baltimore | O124: Baltimore | P124: 2998.3413 | Q124: 35931650 | R124: Government Services | S124: 3
A125: 124 | B125: Inc5000 Company List | C125: Inc5000 Company List | D125: 124 | E125: http://www.inc.com/inc5000list/json/inc5000_2014.json | F125: 21024 | G125: 124 | H125: 74 | I125: =IF(H125<=50,"Small",IF(H125<=200,"Medium",IF(H125<=500,"Large","Enterprise"))) -> Medium | J125: VRx | K125: vrx | L125: Utah | M125: UT | N125: Salt Lake City | O125: Salt Lake City | P125: 2987.2957 | Q125: 89554237 | R125: Health | S125: 3
A126: 125 | B126: Inc5000 Company List | C126: Inc5000 Company List | D126: 125 | E126: http://www.inc.com/inc5000list/json/inc5000_2014.json | F126: 25425 | G126: 125 | H126: 42 | I126: =IF(H126<=50,"Small",IF(H126<=200,"Medium",IF(H126<=500,"Large","Enterprise"))) -> Small | J126: SmackTom.com | K126: smacktomcom | L126: Florida | M126: FL | N126: Miami | O126: Miami | P126: 2963.7255 | Q126: 3125000 | R126: Retail | S126: 1
A127: 126 | B127: Inc5000 Company List | C127: Inc5000 Company List | D127: 126 | E127: http://www.inc.com/inc5000list/json/inc5000_2014.json | F127: 25034 | G127: 126 | H127: 10 | I127: =IF(H127<=50,"Small",IF(H127<=200,"Medium",IF(H127<=500,"Large","Enterprise"))) -> Small | J127: Virtual Fleet Supervisor | K127: virtual-fleet-supervisor | L127: Florida | M127: FL | N127: Oviedo | O127: Orlando FL | P127: 2948.8362 | Q127: 3526101 | R127: Software | S127: 1
A128: 127 | B128: Inc5000 Company List | C128: Inc5000 Company List | D128: 127 | E128: http://www.inc.com/inc5000list/json/inc5000_2014.json | F128: 25283 | G128: 127 | H128: 262 | I128: =IF(H128<=50,"Small",IF(H128<=200,"Medium",IF(H128<=500,"Large","Enterprise"))) -> Large | J128: CareCloud | K128: carecloud | L128: Florida | M128: FL | N128: Miami | O128: Miami | P128: 2939.6153 | Q128: 10455000 | R128: Health | S128: 1
A129: 128 | B129: Inc5000 Company List | C129: Inc5000 Company List | D129: 128 | E129: http://www.inc.com/inc5000list/json/inc5000_2014.json | F129: 24789 | G129: 128 | H129: 64 | I129: =IF(H129<=50,"Small",IF(H129<=200,"Medium",IF(H129<=500,"Large","Enterprise"))) -> Medium | J129: Fueled | K129: fueled | L129: New York | M129: NY | N129: New York | O129: New York City | P129: 2916.7442 | Q129: 6486000 | R129: Advertising & Marketing | S129: 1
A130: 129 | B130: Inc5000 Company List | C130: Inc5000 Company List | D130: 129 | E130: http://www.inc.com/inc5000list/json/inc5000_2014.json | F130: 26484 | G130: 129 | H130: 14 | I130: =IF(H130<=50,"Small",IF(H130<=200,"Medium",IF(H130<=500,"Large","Enterprise"))) -> Small | J130: Bob's Watches | K130: bobs-watches | L130: California | M130: CA | N130: Westminster | O130: Los Angeles | P130: 2861.191 | Q130: 11101120 | R130: Retail | S130: 1
A131: 130 | B131: Inc5000 Company List | C131: Inc5000 Company List | D131: 130 | E131: http://www.inc.com/inc5000list/json/inc5000_2014.json | F131: 24852 | G131: 130 | H131: 6 | I131: =IF(H131<=50,"Small",IF(H131<=200,"Medium",IF(H131<=500,"Large","Enterprise"))) -> Small | J131: CPA Trend | K131: cpa-trend | L131: New York | M131: NY | N131: Howard Beach | O131: New York City | P131: 2842.941 | Q131: 5826876 | R131: Advertising & Marketing | S131: 1
... A136: 135 | B136: Inc5000 Company List | C136: Inc5000 Company List | D136: 135 | E136: http://www.inc.com/inc5000list/json/inc5000_2014.json | F136: 23162 | G136: 135 | H136: 24 | I136: =IF(H136<=50,"Small",IF(H136<=200,"Medium",IF(H136<=500,"Large","Enterprise"))) -> Small | J136: Marketsmith | K136: marketsmith | L136: New Jersey | M136: NJ | N136: Parsippany | O136: New York City | P136: 2752.5555 | Q136: 72908666 | R136: Advertising & Marketing | S136: 2
A137: 136 | B137: Inc5000 Company List | C137: Inc5000 Company List | D137: 136 | E137: http://www.inc.com/inc5000list/json/inc5000_2014.json | F137: 25279 | G137: 136 | H137: 18 | I137: =IF(H137<=50,"Small",IF(H137<=200,"Medium",IF(H137<=500,"Large","Enterprise"))) -> Small | J137: Project Management Academy | K137: project-management-academy | L137: Indiana | M137: IN | N137: West Lafayette | P137: 2752.4901 | Q137: 8094996 | R137: Education | S137: 1
A138: 137 | B138: Inc5000 Company List | C138: Inc5000 Company List | D138: 137 | E138: http://www.inc.com/inc5000list/json/inc5000_2014.json | F138: 24932 | G138: 137 | H138: 25 | I138: =IF(H138<=50,"Small",IF(H138<=200,"Medium",IF(H138<=500,"Large","Enterprise"))) -> Small | J138: Flying Cork Media | K138: flying-cork-media | L138: Pennsylvania | M138: PA | N138: Pittsburgh | O138: Pittsburgh PA | P138: 2745.4166 | Q138: 7502709 | R138: Advertising & Marketing | S138: 1
A139: 138 | B139: Inc5000 Company List | C139: Inc5000 Company List | D139: 138 | E139: http://www.inc.com/inc5000list/json/inc5000_2014.json | F139: 24888 | G139: 138 | H139: 160 | I139: =IF(H139<=50,"Small",IF(H139<=200,"Medium",IF(H139<=500,"Large","Enterprise"))) -> Medium | J139: Motivity Labs | K139: motivity-labs | L139: Texas | M139: TX | N139: Irving | O139: Dallas | P139: 2716.0018 | Q139: 3225899 | R139: IT Services | S139: 1
A140: 139 | B140: Inc5000 Company List | C140: Inc5000 Company List | D140: 139 | E140: http://www.inc.com/inc5000list/json/inc5000_2014.json | F140: 26263 | G140: 139 | H140: 232 | I140: =IF(H140<=50,"Small",IF(H140<=200,"Medium",IF(H140<=500,"Large","Enterprise"))) -> Large | J140: Twilio | K140: twilio | L140: California | M140: CA | N140: San Francisco | O140: San Francisco | P140: 2710.8696 | Q140: 51720000 | R140: Telecommunications | S140: 1
A141: 140 | B141: Inc5000 Company List | C141: Inc5000 Company List | D141: 140 | E141: http://www.inc.com/inc5000list/json/inc5000_2014.json | F141: 25095 | G141: 140 | H141: 20 | I141: =IF(H141<=50,"Small",IF(H141<=200,"Medium",IF(H141<=500,"Large","Enterprise"))) -> Small | J141: Signature Closers | K141: signature-closers | L141: Ohio | M141: OH | N141: Upper Arlington | O141: Columbus OH | P141: 2709.3881 | Q141: 3843580 | R141: Real Estate | S141: 1
A142: 141 | B142: Inc5000 Company List | C142: Inc5000 Company List | D142: 141 | E142: http://www.inc.com/inc5000list/json/inc5000_2014.json | F142: 25749 | G142: 141 | H142: 81 | I142: =IF(H142<=50,"Small",IF(H142<=200,"Medium",IF(H142<=500,"Large","Enterprise"))) -> Medium | J142: PureCars | K142: purecars | L142: South Carolina | M142: SC | N142: Charleston | O142: Charleston-North Charleston SC | P142: 2689.9672 | Q142: 8725985 | R142: Advertising & Marketing | S142: 1
A143: 142 | B143: Inc5000 Company List | C143: Inc5000 Company List | D143: 142 | E143: http://www.inc.com/inc5000list/json/inc5000_2014.json | F143: 25236 | G143: 142 | H143: 96 | I143: =IF(H143<=50,"Small",IF(H143<=200,"Medium",IF(H143<=500,"Large","Enterprise"))) -> Medium | J143: The Cambridge Institute of International Education | K143: the-cambridge-institute-of-international-education | L143: Massachusetts | M143: MA | N143: Waltham | O143: Boston | P143: 2683.3172 | Q143: 9784000 | R143: Education | S143: 1
A144: 143 | B144: Inc5000 Company List | C144: Inc5000 Company List | D144: 143 | E144: http://www.inc.com/inc5000list/json/inc5000_2014.json | F144: 25237 | G144: 143 | H144: 53 | I144: =IF(H144<=50,"Small",IF(H144<=200,"Medium",IF(H144<=500,"Large","Enterprise"))) -> Medium | J144: Market6 | K144: market6 | L144: Illinois | M144: IL | N144: Deerfield | O144: Chicago | P144: 2677.1957 | Q144: 15085838 | R144: Software | S144: 1
A145: 144 | B145: Inc5000 Company List | C145: Inc5000 Company List | D145: 144 | E145: http://www.inc.com/inc5000list/json/inc5000_2014.json | F145: 25594 | G145: 144 | H145: 53 | I145: =IF(H145<=50,"Small",IF(H145<=200,"Medium",IF(H145<=500,"Large","Enterprise"))) -> Medium | J145: LiveRamp | K145: liveramp | L145: California | M145: CA | N145: San Francisco | O145: San Francisco | P145: 2665.2479 | Q145: 21040412 | R145: Advertising & Marketing | S145: 1
A146: 145 | B146: Inc5000 Company List | C146: Inc5000 Company List | D146: 145 | E146: http://www.inc.com/inc5000list/json/inc5000_2014.json | F146: 25620 | G146: 145 | H146: 160 | I146: =IF(H146<=50,"Small",IF(H146<=200,"Medium",IF(H146<=500,"Large","Enterprise"))) -> Medium | J146: MyClean | K146: myclean | L146: New York | M146: NY | N146: New York | O146: New York City | P146: 2646.4033 | Q146: 4399793 | R146: Consumer Products & Services | S146: 1
A147: 146 | B147: Inc5000 Company List | C147: Inc5000 Company List | D147: 146 | E147: http://www.inc.com/inc5000list/json/inc5000_2014.json | F147: 26220 | G147: 146 | H147: 35 | I147: =IF(H147<=50,"Small",IF(H147<=200,"Medium",IF(H147<=500,"Large","Enterprise"))) -> Small | J147: PresenceLearning | K147: presencelearning | L147: California | M147: CA | N147: San Francisco | O147: San Francisco | P147: 2634.2593 | Q147: 5906000 | R147: Education | S147: 1
A148: 147 | B148: Inc5000 Company List | C148: Inc5000 Company List | D148: 147 | E148: http://www.inc.com/inc5000list/json/inc5000_2014.json | F148: 26517 | G148: 147 | H148: 140 | I148: =IF(H148<=50,"Small",IF(H148<=200,"Medium",IF(H148<=500,"Large","Enterprise"))) -> Medium | J148: Residential Capital Management | K148: residential-capital-management | L148: Georgia | M148: GA | N148: Atlanta | O148: Atlanta | P148: 2626.018 | Q148: 30167124 | R148: Real Estate | S148: 1
A149: 148 | B149: Inc5000 Company List | C149: Inc5000 Company List | D149: 148 | E149: http://www.inc.com/inc5000list/json/inc5000_2014.json | F149: 25293 | G149: 148 | H149: 14 | I149: =IF(H149<=50,"Small",IF(H149<=200,"Medium",IF(H149<=500,"Large","Enterprise"))) -> Small | J149: Total Technology Solutions Group | K149: total-technology-solutions-group | L149: Illinois | M149: IL | N149: St. Charles | O149: Chicago | P149: 2608.0908 | Q149: 3115496 | R149: Business Products & Services | S149: 1
... A163: 162 | B163: Inc5000 Company List | C163: Inc5000 Company List | D163: 162 | E163: http://www.inc.com/inc5000list/json/inc5000_2014.json | F163: 21880 | G163: 162 | H163: 24 | I163: =IF(H163<=50,"Small",IF(H163<=200,"Medium",IF(H163<=500,"Large","Enterprise"))) -> Small | J163: ECHO Health | K163: echo-health | L163: Ohio | M163: OH | N163: Westlake | O163: Cleveland | P163: 2509.1757 | Q163: 46984261 | R163: Health | S163: 3
A164: 163 | B164: Inc5000 Company List | C164: Inc5000 Company List | D164: 163 | E164: http://www.inc.com/inc5000list/json/inc5000_2014.json | F164: 25153 | G164: 163 | H164: 75 | I164: =IF(H164<=50,"Small",IF(H164<=200,"Medium",IF(H164<=500,"Large","Enterprise"))) -> Medium | J164: Marathon TS | K164: marathon-ts | L164: Virginia | M164: VA | N164: Kilmarnock | P164: 2507.7517 | Q164: 6821409 | R164: Government Services | S164: 1
A165: 164 | B165: Inc5000 Company List | C165: Inc5000 Company List | D165: 164 | E165: http://www.inc.com/inc5000list/json/inc5000_2014.json | F165: 23033 | G165: 164 | H165: 8 | I165: =IF(H165<=50,"Small",IF(H165<=200,"Medium",IF(H165<=500,"Large","Enterprise"))) -> Small | J165: AudioMicro | K165: audiomicro | L165: California | M165: CA | N165: Sherman Oaks | O165: Los Angeles | P165: 2495.6297 | Q165: 5426086 | R165: Media | S165: 2
A166: 165 | B166: Inc5000 Company List | C166: Inc5000 Company List | D166: 165 | E166: http://www.inc.com/inc5000list/json/inc5000_2014.json | F166: 25024 | G166: 165 | H166: 6 | I166: =IF(H166<=50,"Small",IF(H166<=200,"Medium",IF(H166<=500,"Large","Enterprise"))) -> Small | J166: LED Supply | K166: led-supply | L166: Colorado | M166: CO | N166: Lakewood | O166: Denver | P166: 2474.0559 | Q166: 2877743 | R166: Business Products & Services | S166: 1
A167: 166 | B167: Inc5000 Company List | C167: Inc5000 Company List | D167: 166 | E167: http://www.inc.com/inc5000list/json/inc5000_2014.json | F167: 26487 | G167: 166 | H167: 6 | I167: =IF(H167<=50,"Small",IF(H167<=200,"Medium",IF(H167<=500,"Large","Enterprise"))) -> Small | J167: LeGault Homes | K167: legault-homes | L167: Virginia | M167: VA | N167: Glen Allen | O167: Richmond VA | P167: 2455.075 | Q167: 7660396 | R167: Real Estate | S167: 1
A168: 167 | B168: Inc5000 Company List | C168: Inc5000 Company List | D168: 167 | E168: http://www.inc.com/inc5000list/json/inc5000_2014.json | F168: 25384 | G168: 167 | H168: 9 | I168: =IF(H168<=50,"Small",IF(H168<=200,"Medium",IF(H168<=500,"Large","Enterprise"))) -> Small | J168: Forte International Tax | K168: forte-international-tax | L168: Illinois | M168: IL | N168: Evanston | O168: Chicago | P168: 2447.3722 | Q168: 3475711 | R168: Financial Services | S168: 1
A169: 168 | B169: Inc5000 Company List | C169: Inc5000 Company List | D169: 168 | E169: http://www.inc.com/inc5000list/json/inc5000_2014.json | F169: 25488 | G169: 168 | H169: 31 | I169: =IF(H169<=50,"Small",IF(H169<=200,"Medium",IF(H169<=500,"Large","Enterprise"))) -> Small | J169: Paradigm Mechanical | K169: paradigm-mechanical | L169: California | M169: CA | N169: Lemon Grove | O169: San Diego | P169: 2439.5443 | Q169: 5250000 | R169: Construction | S169: 1
A170: 169 | B170: Inc5000 Company List | C170: Inc5000 Company List | D170: 169 | E170: http://www.inc.com/inc5000list/json/inc5000_2014.json | F170: 22992 | G170: 169 | H170: 45 | I170: =IF(H170<=50,"Small",IF(H170<=200,"Medium",IF(H170<=500,"Large","Enterprise"))) -> Small | J170: Finance Store | K170: finance-store | L170: California | M170: CA | N170: Santa Ana | O170: Los Angeles | P170: 2436.3022 | Q170: 4590707 | R170: Financial Services | S170: 2
A171: 170 | B171: Inc5000 Company List | C171: Inc5000 Company List | D171: 170 | E171: http://www.inc.com/inc5000list/json/inc5000_2014.json | F171: 25512 | G171: 170 | H171: 27 | I171: =IF(H171<=50,"Small",IF(H171<=200,"Medium",IF(H171<=500,"Large","Enterprise"))) -> Small | J171: Pure Incubation | K171: pure-incubation | L171: Massachusetts | M171: MA | N171: Topsfield | O171: Boston | P171: 2427.7792 | Q171: 4696917 | R171: Advertising & Marketing | S171: 1
A172: 171 | B172: Inc5000 Company List | C172: Inc5000 Company List | D172: 171 | E172: http://www.inc.com/inc5000list/json/inc5000_2014.json | F172: 25313 | G172: 171 | H172: 10 | I172: =IF(H172<=50,"Small",IF(H172<=200,"Medium",IF(H172<=500,"Large","Enterprise"))) -> Small | J172: Kohana Coffee | K172: kohana-coffee | L172: Texas | M172: TX | N172: Austin | O172: Austin | P172: 2416.7762 | Q172: 2825786 | R172: Food & Beverage | S172: 1
A173: 172 | B173: Inc5000 Company List | C173: Inc5000 Company List | D173: 172 | E173: http://www.inc.com/inc5000list/json/inc5000_2014.json | F173: 26221 | G173: 172 | H173: 107 | I173: =IF(H173<=50,"Small",IF(H173<=200,"Medium",IF(H173<=500,"Large","Enterprise"))) -> Medium | J173: Ensighten | K173: ensighten | L173: California | M173: CA | N173: Cupertino | O173: San Jose | P173: 2415.8055 | Q173: 8277000 | R173: Advertising & Marketing | S173: 1
A174: 173 | B174: Inc5000 Company List | C174: Inc5000 Company List | D174: 173 | E174: http://www.inc.com/inc5000list/json/inc5000_2014.json | F174: 26167 | G174: 173 | H174: 123 | I174: =IF(H174<=50,"Small",IF(H174<=200,"Medium",IF(H174<=500,"Large","Enterprise"))) -> Medium | J174: Pathway Genomics | K174: pathway-genomics | L174: California | M174: CA | N174: San Diego | O174: San Diego | P174: 2415.5285 | Q174: 14426053 | R174: Health | S174: 1
A175: 174 | B175: Inc5000 Company List | C175: Inc5000 Company List | D175: 174 | E175: http://www.inc.com/inc5000list/json/inc5000_2014.json | F175: 24957 | G175: 174 | H175: 325 | I175: =IF(H175<=50,"Small",IF(H175<=200,"Medium",IF(H175<=500,"Large","Enterprise"))) -> Large | J175: CenseoHealth | K175: censeohealth | L175: Texas | M175: TX | N175: Dallas | O175: Dallas | P175: 2406.9499 | Q175: 117230240 | R175: Health | S175: 1
A176: 175 | B176: Inc5000 Company List | C176: Inc5000 Company List | D176: 175 | E176: http://www.inc.com/inc5000list/json/inc5000_2014.json | F176: 26180 | G176: 175 | H176: 270 | I176: =IF(H176<=50,"Small",IF(H176<=200,"Medium",IF(H176<=500,"Large","Enterprise"))) -> Large | J176: 3A/WorldWide | K176: 3aworldwide | L176: Florida | M176: FL | N176: Miami | O176: Miami | P176: 2402.7683 | Q176: 57568000 | R176: Advertising & Marketing | S176: 1
... A188: 187 | B188: Inc5000 Company List | C188: Inc5000 Company List | D188: 187 | E188: http://www.inc.com/inc5000list/json/inc5000_2014.json | F188: 25128 | G188: 187 | H188: 15 | I188: =IF(H188<=50,"Small",IF(H188<=200,"Medium",IF(H188<=500,"Large","Enterprise"))) -> Small | J188: NITS Solutions | K188: nits-solutions | L188: Michigan | M188: MI | N188: Novi | O188: Detroit | P188: 2291.3176 | Q188: 2775411 | R188: IT Services | S188: 1
A189: 188 | B189: Inc5000 Company List | C189: Inc5000 Company List | D189: 188 | E189: http://www.inc.com/inc5000list/json/inc5000_2014.json | F189: 25869 | G189: 188 | H189: 18 | I189: =IF(H189<=50,"Small",IF(H189<=200,"Medium",IF(H189<=500,"Large","Enterprise"))) -> Small | J189: Paramount Lodging Advisors | K189: paramount-lodging-advisors | L189: Illinois | M189: IL | N189: Chicago | P189: 2288.3653 | Q189: 2465605 | R189: Real Estate | S189: 1
A190: 189 | B190: Inc5000 Company List | C190: Inc5000 Company List | D190: 189 | E190: http://www.inc.com/inc5000list/json/inc5000_2014.json | F190: 25783 | G190: 189 | H190: 35 | I190: =IF(H190<=50,"Small",IF(H190<=200,"Medium",IF(H190<=500,"Large","Enterprise"))) -> Small | J190: EmazingLights | K190: emazinglights | L190: California | M190: CA | N190: Anaheim | O190: Los Angeles | P190: 2281.335 | Q190: 5842010 | R190: Retail | S190: 1
A191: 190 | B191: Inc5000 Company List | C191: Inc5000 Company List | D191: 190 | E191: http://www.inc.com/inc5000list/json/inc5000_2014.json | F191: 26528 | G191: 190 | H191: 35 | I191: =IF(H191<=50,"Small",IF(H191<=200,"Medium",IF(H191<=500,"Large","Enterprise"))) -> Small | J191: Level Interactive | K191: level-interactive | L191: Pennsylvania | M191: PA | N191: Pittsburgh | O191: Pittsburgh PA | P191: 2258.7014 | Q191: 11958616 | R191: Advertising & Marketing | S191: 1
A192: 191 | B192: Inc5000 Company List | C192: Inc5000 Company List | D192: 191 | E192: http://www.inc.com/inc5000list/json/inc5000_2014.json | F192: 26255 | G192: 191 | H192: 75 | I192: =IF(H192<=50,"Small",IF(H192<=200,"Medium",IF(H192<=500,"Large","Enterprise"))) -> Medium | J192: shopkick | K192: shopkick | L192: California | M192: CA | N192: Redwood City | O192: San Francisco | P192: 2250.0409 | Q192: 26319118 | R192: Retail | S192: 1
A193: 192 | B193: Inc5000 Company List | C193: Inc5000 Company List | D193: 192 | E193: http://www.inc.com/inc5000list/json/inc5000_2014.json | F193: 25486 | G193: 192 | H193: 129 | I193: =IF(H193<=50,"Small",IF(H193<=200,"Medium",IF(H193<=500,"Large","Enterprise"))) -> Medium | J193: TekWissen | K193: tekwissen | L193: Michigan | M193: MI | N193: Ann Arbor | O193: Ann Arbor MI | P193: 2236.1753 | Q193: 7802802 | R193: IT Services | S193: 1
A194: 193 | B194: Inc5000 Company List | C194: Inc5000 Company List | D194: 193 | E194: http://www.inc.com/inc5000list/json/inc5000_2014.json | F194: 25501 | G194: 193 | H194: 15 | I194: =IF(H194<=50,"Small",IF(H194<=200,"Medium",IF(H194<=500,"Large","Enterprise"))) -> Small | J194: VPCinnovations | K194: vpcinnovations | L194: Wisconsin | M194: WI | N194: Mount Pleasant | O194: Chicago | P194: 2234.3619 | Q194: 5390952 | R194: Computer Hardware | S194: 1
A195: 194 | B195: Inc5000 Company List | C195: Inc5000 Company List | D195: 194 | E195: http://www.inc.com/inc5000list/json/inc5000_2014.json | F195: 25433 | G195: 194 | H195: 42 | I195: =IF(H195<=50,"Small",IF(H195<=200,"Medium",IF(H195<=500,"Large","Enterprise"))) -> Small | J195: Clean Energy Collective | K195: clean-energy-collective | L195: Colorado | M195: CO | N195: Boulder | O195: Boulder CO | P195: 2216.9118 | Q195: 9453000 | R195: Energy | S195: 1
A196: 195 | B196: Inc5000 Company List | C196: Inc5000 Company List | D196: 195 | E196: http://www.inc.com/inc5000list/json/inc5000_2014.json | F196: 26030 | G196: 195 | H196: 13 | I196: =IF(H196<=50,"Small",IF(H196<=200,"Medium",IF(H196<=500,"Large","Enterprise"))) -> Small | J196: Silver Bullet Construction | K196: silver-bullet-construction | L196: Texas | M196: TX | N196: Dalworthington Garden | O196: Dallas | P196: 2215.5963 | Q196: 2524000 | R196: Construction | S196: 1
A197: 196 | B197: Inc5000 Company List | C197: Inc5000 Company List | D197: 196 | E197: http://www.inc.com/inc5000list/json/inc5000_2014.json | F197: 26326 | G197: 196 | H197: 48 | I197: =IF(H197<=50,"Small",IF(H197<=200,"Medium",IF(H197<=500,"Large","Enterprise"))) -> Small | J197: Aegis Corps | K197: aegis-corps | L197: Virginia | M197: VA | N197: Chantilly | O197: Washington DC | P197: 2208.3868 | Q197: 2900488 | R197: Government Services | S197: 1
A198: 197 | B198: Inc5000 Company List | C198: Inc5000 Company List | D198: 197 | E198: http://www.inc.com/inc5000list/json/inc5000_2014.json | F198: 22899 | G198: 197 | H198: 300 | I198: =IF(H198<=50,"Small",IF(H198<=200,"Medium",IF(H198<=500,"Large","Enterprise"))) -> Large | J198: uBreakiFix | K198: ubreakifix | L198: Florida | M198: FL | N198: Orlando | O198: Orlando FL | P198: 2188.8349 | Q198: 26472870 | R198: Retail | S198: 2
A199: 198 | B199: Inc5000 Company List | C199: Inc5000 Company List | D199: 198 | E199: http://www.inc.com/inc5000list/json/inc5000_2014.json | F199: 25037 | G199: 198 | H199: 302 | I199: =IF(H199<=50,"Small",IF(H199<=200,"Medium",IF(H199<=500,"Large","Enterprise"))) -> Large | J199: Culture.Service.Growth. | K199: cultureservicegrowth | L199: Texas | M199: TX | N199: San Antonio | O199: San Antonio TX | P199: 2182.0898 | Q199: 7993065 | R199: Business Products & Services | S199: 1
A200: 199 | B200: Inc5000 Company List | C200: Inc5000 Company List | D200: 199 | E200: http://www.inc.com/inc5000list/json/inc5000_2014.json | F200: 21023 | G200: 199 | H200: 72 | I200: =IF(H200<=50,"Small",IF(H200<=200,"Medium",IF(H200<=500,"Large","Enterprise"))) -> Medium | J200: CardCash.com | K200: cardcashcom | L200: New Jersey | M200: NJ | N200: Brick | O200: New York City | P200: 2181.7178 | Q200: 55788000 | R200: Consumer Products & Services | S200: 3
A201: 200 | B201: Inc5000 Company List | C201: Inc5000 Company List | D201: 200 | E201: http://www.inc.com/inc5000list/json/inc5000_2014.json | F201: 26083 | G201: 200 | H201: 450 | I201: =IF(H201<=50,"Small",IF(H201<=200,"Medium",IF(H201<=500,"Large","Enterprise"))) -> Large | J201: Protein Bar | K201: protein-bar | L201: Illinois | M201: IL | N201: Chicago | O201: Chicago | P201: 2181.6917 | Q201: 14211083 | R201: Food & Beverage | S201: 1
... A268: 267 | B268: Inc5000 Company List | C268: Inc5000 Company List | D268: 267 | E268: http://www.inc.com/inc5000list/json/inc5000_2014.json | F268: 25674 | G268: 267 | H268: 142 | I268: =IF(H268<=50,"Small",IF(H268<=200,"Medium",IF(H268<=500,"Large","Enterprise"))) -> Medium | J268: Human Movement Management | K268: human-movement-management | L268: Colorado | M268: CO | N268: Louisville | O268: Boulder CO | P268: 1724.3576 | Q268: 9054816 | R268: Consumer Products & Services | S268: 1
A269: 268 | B269: Inc5000 Company List | C269: Inc5000 Company List | D269: 268 | E269: http://www.inc.com/inc5000list/json/inc5000_2014.json | F269: 25622 | G269: 268 | H269: 47 | I269: =IF(H269<=50,"Small",IF(H269<=200,"Medium",IF(H269<=500,"Large","Enterprise"))) -> Small | J269: Allegheny Science & Technology | K269: allegheny-science-technology | L269: West Virginia | M269: WV | N269: Bridgeport | P269: 1723.2877 | Q269: 7023359 | R269: Government Services | S269: 1
A270: 269 | B270: Inc5000 Company List | C270: Inc5000 Company List | D270: 269 | E270: http://www.inc.com/inc5000list/json/inc5000_2014.json | F270: 22994 | G270: 269 | H270: 110 | I270: =IF(H270<=50,"Small",IF(H270<=200,"Medium",IF(H270<=500,"Large","Enterprise"))) -> Medium | J270: Hudl | K270: hudl | L270: Nebraska | M270: NE | N270: Lincoln | O270: Lincoln NE | P270: 1707.5863 | Q270: 22326800 | R270: Software | S270: 2
A271: 270 | B271: Inc5000 Company List | C271: Inc5000 Company List | D271: 270 | E271: http://www.inc.com/inc5000list/json/inc5000_2014.json | F271: 25092 | G271: 270 | H271: 69 | I271: =IF(H271<=50,"Small",IF(H271<=200,"Medium",IF(H271<=500,"Large","Enterprise"))) -> Medium | J271: GuideSpark | K271: guidespark | L271: California | M271: CA | N271: Menlo Park | O271: San Francisco | P271: 1703.5556 | Q271: 4058000 | R271: Software | S271: 1
A272: 271 | B272: Inc5000 Company List | C272: Inc5000 Company List | D272: 271 | E272: http://www.inc.com/inc5000list/json/inc5000_2014.json | F272: 25160 | G272: 271 | H272: 25 | I272: =IF(H272<=50,"Small",IF(H272<=200,"Medium",IF(H272<=500,"Large","Enterprise"))) -> Small | J272: Optimus Technology | K272: optimus-technology | L272: Maryland | M272: MD | N272: Columbia | O272: Baltimore | P272: 1701.5569 | Q272: 2086383 | R272: IT Services | S272: 1
A273: 272 | B273: Inc5000 Company List | C273: Inc5000 Company List | D273: 272 | E273: http://www.inc.com/inc5000list/json/inc5000_2014.json | F273: 26438 | G273: 272 | H273: 22 | I273: =IF(H273<=50,"Small",IF(H273<=200,"Medium",IF(H273<=500,"Large","Enterprise"))) -> Small | J273: Luxe Royale | K273: luxe-royale | L273: Nevada | M273: NV | N273: Las Vegas | O273: Las Vegas-Paradise NV | P273: 1696.071 | Q273: 2265115 | R273: Travel & Hospitality | S273: 1
A274: 273 | B274: Inc5000 Company List | C274: Inc5000 Company List | D274: 273 | E274: http://www.inc.com/inc5000list/json/inc5000_2014.json | F274: 24928 | G274: 273 | H274: 8 | I274: =IF(H274<=50,"Small",IF(H274<=200,"Medium",IF(H274<=500,"Large","Enterprise"))) -> Small | J274: SoluComp | K274: solucomp | L274: Illinois | M274: IL | N274: South Barrington | O274: Chicago | P274: 1694.0032 | Q274: 2213172 | R274: Telecommunications | S274: 1
A275: 274 | B275: Inc5000 Company List | C275: Inc5000 Company List | D275: 274 | E275: http://www.inc.com/inc5000list/json/inc5000_2014.json | F275: 24922 | G275: 274 | H275: 15 | I275: =IF(H275<=50,"Small",IF(H275<=200,"Medium",IF(H275<=500,"Large","Enterprise"))) -> Small | J275: RPM Freight Systems | K275: rpm-freight-systems | L275: Michigan | M275: MI | N275: Royal Oak | O275: Detroit | P275: 1683.3663 | Q275: 4647952 | R275: Logistics & Transportation | S275: 1
A276: 275 | B276: Inc5000 Company List | C276: Inc5000 Company List | D276: 275 | E276: http://www.inc.com/inc5000list/json/inc5000_2014.json | F276: 25684 | G276: 275 | H276: 24 | I276: =IF(H276<=50,"Small",IF(H276<=200,"Medium",IF(H276<=500,"Large","Enterprise"))) -> Small | J276: Motivational Press | K276: motivational-press | L276: California | M276: CA | N276: Carlsbad | O276: San Diego | P276: 1675 | Q276: 2343000 | R276: Media | S276: 1
A277: 276 | B277: Inc5000 Company List | C277: Inc5000 Company List | D277: 276 | E277: http://www.inc.com/inc5000list/json/inc5000_2014.json | F277: 25951 | G277: 276 | H277: 41 | I277: =IF(H277<=50,"Small",IF(H277<=200,"Medium",IF(H277<=500,"Large","Enterprise"))) -> Small | J277: Accordant Media | K277: accordant-media | L277: New York | M277: NY | N277: New York | O277: New York City | P277: 1663.0114 | Q277: 27119347 | R277: Advertising & Marketing | S277: 1
A278: 277 | B278: Inc5000 Company List | C278: Inc5000 Company List | D278: 277 | E278: http://www.inc.com/inc5000list/json/inc5000_2014.json | F278: 23059 | G278: 277 | H278: 100 | I278: =IF(H278<=50,"Small",IF(H278<=200,"Medium",IF(H278<=500,"Large","Enterprise"))) -> Medium | J278: iQuanti | K278: iquanti | L278: New Jersey | M278: NJ | N278: Hoboken | O278: New York City | P278: 1654.4182 | Q278: 5001355 | R278: Advertising & Marketing | S278: 2
A279: 278 | B279: Inc5000 Company List | C279: Inc5000 Company List | D279: 278 | E279: http://www.inc.com/inc5000list/json/inc5000_2014.json | F279: 26075 | G279: 278 | H279: 268 | I279: =IF(H279<=50,"Small",IF(H279<=200,"Medium",IF(H279<=500,"Large","Enterprise"))) -> Large | J279: Bareburger | K279: bareburger | L279: New York | M279: NY | N279: Long Island City | O279: New York City | P279: 1652.3627 | Q279: 31150000 | R279: Food & Beverage | S279: 1
A280: 279 | B280: Inc5000 Company List | C280: Inc5000 Company List | D280: 279 | E280: http://www.inc.com/inc5000list/json/inc5000_2014.json | F280: 22972 | G280: 279 | H280: 74 | I280: =IF(H280<=50,"Small",IF(H280<=200,"Medium",IF(H280<=500,"Large","Enterprise"))) -> Medium | J280: BMA | K280: bma | L280: Kansas | M280: KS | N280: Leavenworth | O280: Kansas City MO-KS | P280: 1651.8539 | Q280: 14580032 | R280: Government Services | S280: 2
A281: 280 | B281: Inc5000 Company List | C281: Inc5000 Company List | D281: 280 | E281: http://www.inc.com/inc5000list/json/inc5000_2014.json | F281: 22959 | G281: 280 | H281: 73 | I281: =IF(H281<=50,"Small",IF(H281<=200,"Medium",IF(H281<=500,"Large","Enterprise"))) -> Medium | J281: CoverMyMeds | K281: covermymeds | L281: Ohio | M281: OH | N281: Twinsburg | O281: Akron OH | P281: 1647.939 | Q281: 18691673 | R281: Health | S281: 2
... A297: 296 | B297: Inc5000 Company List | C297: Inc5000 Company List | D297: 296 | E297: http://www.inc.com/inc5000list/json/inc5000_2014.json | F297: 26314 | G297: 296 | H297: 2 | I297: =IF(H297<=50,"Small",IF(H297<=200,"Medium",IF(H297<=500,"Large","Enterprise"))) -> Small | J297: AcquisitionsAndRenewals.com | K297: acquisitionsandrenewalscom | L297: Nevada | M297: NV | N297: Henderson | O297: Las Vegas-Paradise NV | P297: 1548.8424 | Q297: 4628284 | R297: Telecommunications | S297: 1
A298: 297 | B298: Inc5000 Company List | C298: Inc5000 Company List | D298: 297 | E298: http://www.inc.com/inc5000list/json/inc5000_2014.json | F298: 22947 | G298: 297 | H298: 19 | I298: =IF(H298<=50,"Small",IF(H298<=200,"Medium",IF(H298<=500,"Large","Enterprise"))) -> Small | J298: Bio Soil Enhancers | K298: bio-soil-enhancers | L298: Mississippi | M298: MS | N298: Hattiesburg | P298: 1538.9036 | Q298: 7811162 | R298: Manufacturing | S298: 2
A299: 298 | B299: Inc5000 Company List | C299: Inc5000 Company List | D299: 298 | E299: http://www.inc.com/inc5000list/json/inc5000_2014.json | F299: 26256 | G299: 298 | H299: 23 | I299: =IF(H299<=50,"Small",IF(H299<=200,"Medium",IF(H299<=500,"Large","Enterprise"))) -> Small | J299: Cogito | K299: cogito | L299: Massachusetts | M299: MA | N299: Boston | O299: Boston | P299: 1528.9871 | Q299: 2524930 | R299: Software | S299: 1
A300: 299 | B300: Inc5000 Company List | C300: Inc5000 Company List | D300: 299 | E300: http://www.inc.com/inc5000list/json/inc5000_2014.json | F300: 26250 | G300: 299 | H300: 35 | I300: =IF(H300<=50,"Small",IF(H300<=200,"Medium",IF(H300<=500,"Large","Enterprise"))) -> Small | J300: MorrisCore | K300: morriscore | L300: Florida | M300: FL | N300: Pompano Beach | O300: Miami | P300: 1520.2761 | Q300: 2064653 | R300: Advertising & Marketing | S300: 1
A301: 300 | B301: Inc5000 Company List | C301: Inc5000 Company List | D301: 300 | E301: http://www.inc.com/inc5000list/json/inc5000_2014.json | F301: 24920 | G301: 300 | H301: 7 | I301: =IF(H301<=50,"Small",IF(H301<=200,"Medium",IF(H301<=500,"Large","Enterprise"))) -> Small | J301: Noi Solutions | K301: noi-solutions | L301: New York | M301: NY | N301: New York | O301: New York City | P301: 1519.4793 | Q301: 22833994 | R301: Business Products & Services | S301: 1
A302: 301 | B302: Inc5000 Company List | C302: Inc5000 Company List | D302: 301 | E302: http://www.inc.com/inc5000list/json/inc5000_2014.json | F302: 25993 | G302: 301 | H302: 32 | I302: =IF(H302<=50,"Small",IF(H302<=200,"Medium",IF(H302<=500,"Large","Enterprise"))) -> Small | J302: KeVita Sparkling Probiotic Drinks | K302: kevita-sparkling-probiotic-drinks | L302: California | M302: CA | N302: Oxnard | O302: Oxnard-Thousand Oaks-Ventura CA | P302: 1518.5507 | Q302: 11168000 | R302: Food & Beverage | S302: 1
A303: 302 | B303: Inc5000 Company List | C303: Inc5000 Company List | D303: 302 | E303: http://www.inc.com/inc5000list/json/inc5000_2014.json | F303: 25740 | G303: 302 | H303: 12 | I303: =IF(H303<=50,"Small",IF(H303<=200,"Medium",IF(H303<=500,"Large","Enterprise"))) -> Small | J303: HoverCam | K303: hovercam | L303: California | M303: CA | N303: San Diego | O303: San Diego | P303: 1517.0231 | Q303: 4760241 | R303: Manufacturing | S303: 1
A304: 303 | B304: Inc5000 Company List | C304: Inc5000 Company List | D304: 303 | E304: http://www.inc.com/inc5000list/json/inc5000_2014.json | F304: 21205 | G304: 303 | H304: 10 | I304: =IF(H304<=50,"Small",IF(H304<=200,"Medium",IF(H304<=500,"Large","Enterprise"))) -> Small | J304: Apex Resources | K304: apex-resources | L304: Texas | M304: TX | N304: Dallas | O304: Dallas | P304: 1515.4893 | Q304: 25450095 | R304: Manufacturing | S304: 3
A305: 304 | B305: Inc5000 Company List | C305: Inc5000 Company List | D305: 304 | E305: http://www.inc.com/inc5000list/json/inc5000_2014.json | F305: 25708 | G305: 304 | H305: 25 | I305: =IF(H305<=50,"Small",IF(H305<=200,"Medium",IF(H305<=500,"Large","Enterprise"))) -> Small | J305: SiteCompli | K305: sitecompli | L305: New York | M305: NY | N305: New York | O305: New York City | P305: 1512.312 | Q305: 5126072 | R305: Software | S305: 1
A306: 305 | B306: Inc5000 Company List | C306: Inc5000 Company List | D306: 305 | E306: http://www.inc.com/inc5000list/json/inc5000_2014.json | F306: 21597 | G306: 305 | H306: 80 | I306: =IF(H306<=50,"Small",IF(H306<=200,"Medium",IF(H306<=500,"Large","Enterprise"))) -> Medium | J306: Clearleap | K306: clearleap | L306: Georgia | M306: GA | N306: Duluth | O306: Atlanta | P306: 1509.6721 | Q306: 9819000 | R306: Software | S306: 3
A307: 306 | B307: Inc5000 Company List | C307: Inc5000 Company List | D307: 306 | E307: http://www.inc.com/inc5000list/json/inc5000_2014.json | F307: 22988 | G307: 306 | H307: 15 | I307: =IF(H307<=50,"Small",IF(H307<=200,"Medium",IF(H307<=500,"Large","Enterprise"))) -> Small | J307: StartFinder | K307: startfinder | L307: Maryland | M307: MD | N307: Rockville | O307: Washington DC | P307: 1509.4059 | Q307: 3251000 | R307: Human Resources | S307: 2
A308: 307 | B308: Inc5000 Company List | C308: Inc5000 Company List | D308: 307 | E308: http://www.inc.com/inc5000list/json/inc5000_2014.json | F308: 21314 | G308: 307 | H308: 703 | I308: =IF(H308<=50,"Small",IF(H308<=200,"Medium",IF(H308<=500,"Large","Enterprise"))) -> Enterprise | J308: LongView International Technology Solutions | K308: longview-international-technology-solutions | L308: Virginia | M308: VA | N308: Alexandria | O308: Washington DC | P308: 1505.6112 | Q308: 128269211 | R308: Government Services | S308: 2
A309: 308 | B309: Inc5000 Company List | C309: Inc5000 Company List | D309: 308 | E309: http://www.inc.com/inc5000list/json/inc5000_2014.json | F309: 25239 | G309: 308 | H309: 188 | I309: =IF(H309<=50,"Small",IF(H309<=200,"Medium",IF(H309<=500,"Large","Enterprise"))) -> Medium | J309: Softhq | K309: softhq | L309: California | M309: CA | N309: San Diego | O309: San Diego | P309: 1496.7527 | Q309: 16058111 | R309: IT Services | S309: 1
A310: 309 | B310: Inc5000 Company List | C310: Inc5000 Company List | D310: 309 | E310: http://www.inc.com/inc5000list/json/inc5000_2014.json | F310: 25732 | G310: 309 | H310: 24 | I310: =IF(H310<=50,"Small",IF(H310<=200,"Medium",IF(H310<=500,"Large","Enterprise"))) -> Small | J310: EveryMundo | K310: everymundo | L310: Florida | M310: FL | N310: Miami | O310: Miami | P310: 1495.2936 | Q310: 2454423 | R310: Advertising & Marketing | S310: 1
... A702: 701 | B702: Inc5000 Company List | C702: Inc5000 Company List | D702: 701 | E702: http://www.inc.com/inc5000list/json/inc5000_2014.json | F702: 23173 | G702: 701 | H702: 22 | I702: =IF(H702<=50,"Small",IF(H702<=200,"Medium",IF(H702<=500,"Large","Enterprise"))) -> Small | J702: Caneel Group | K702: caneel-group | L702: New Jersey | M702: NJ | N702: Gibbsboro | O702: Philadelphia | P702: 645.4948 | Q702: 6225075 | R702: Financial Services | S702: 2
A703: 702 | B703: Inc5000 Company List | C703: Inc5000 Company List | D703: 702 | E703: http://www.inc.com/inc5000list/json/inc5000_2014.json | F703: 21342 | G703: 702 | H703: 70 | I703: =IF(H703<=50,"Small",IF(H703<=200,"Medium",IF(H703<=500,"Large","Enterprise"))) -> Medium | J703: Wellness Corporate Solutions | K703: wellness-corporate-solutions | L703: Maryland | M703: MD | N703: Bethesda | P703: 643.7388 | Q703: 12645835 | R703: Health | S703: 3
A704: 703 | B704: Inc5000 Company List | C704: Inc5000 Company List | D704: 703 | E704: http://www.inc.com/inc5000list/json/inc5000_2014.json | F704: 26365 | G704: 703 | H704: 26 | I704: =IF(H704<=50,"Small",IF(H704<=200,"Medium",IF(H704<=500,"Large","Enterprise"))) -> Small | J704: Ready Set Rocket | K704: ready-set-rocket | L704: New York | M704: NY | N704: New York | O704: New York City | P704: 643.7046 | Q704: 3071500 | R704: Advertising & Marketing | S704: 1
...

Sheet Data Dictonary
B1: Company | C1: Rank | D1: Workers | E1: Revenue | F1: Growth | G1: Industry | H1: State | I1: City | J1: Metro | K1: Years on List | L1: id | M1: url

Sheet Data Quality
A1: Company | B1: =COUNTBLANK(Inc5000_Business_Analysis.xlsx!J2:J5001) -> 0 | F1: METRIC | G1: MIN | H1: MAX
A2: Rank | B2: =COUNTBLANK(Inc5000_Business_Analysis.xlsx!H2:H5001) -> 0 | F2: Revenue | G2: =MIN(Inc5000_Business_Analysis.xlsx!Q2:Q5001) -> 1953000 | H2: =MAX(Inc5000_Business_Analysis.xlsx!Q2:Q5001) -> 5528202691
A3: Workers | B3: =COUNTBLANK(Inc5000_Business_Analysis.xlsx!I2:I5001) -> 0 | F3: Growth | G3: =MIN(Inc5000_Business_Analysis.xlsx!P2:P5001) -> 42.447 | H3: =MAX(Inc5000_Business_Analysis.xlsx!P2:P5001) -> 158956.91
A4: Revenue | B4: =COUNTBLANK(Inc5000_Business_Analysis.xlsx!Q2:Q5001) -> 0 | F4: Workers | G4: =MIN(Inc5000_Business_Analysis.xlsx!I2:I5001) -> 0 | H4: =MAX(Inc5000_Business_Analysis.xlsx!I2:I5001) -> 34219
A5: Growth | B5: =COUNTBLANK(Inc5000_Business_Analysis.xlsx!P2:P5001) -> 0 | F5: Rank | G5: =MIN(Inc5000_Business_Analysis.xlsx!H2:H5001) -> 1 | H5: =MAX(Inc5000_Business_Analysis.xlsx!H2:H5001) -> 5000
A6: Industry | B6: =COUNTBLANK(Inc5000_Business_Analysis.xlsx!R2:R5001) -> 0 | F6: Years on List | G6: =MIN(Inc5000_Business_Analysis.xlsx!S2:S5001) -> 1 | H6: =MAX(Inc5000_Business_Analysis.xlsx!S2:S5001) -> 12
A7: State | B7: =COUNTBLANK(Inc5000_Business_Analysis.xlsx!L2:L5001) -> 0
A8: City | B8: =COUNTBLANK(Inc5000_Business_Analysis.xlsx!N2:N5001) -> 0
A9: Metro | B9: =COUNTBLANK(Inc5000_Business_Analysis.xlsx!O2:O5001) -> 58
A10: Years on List | B10: =COUNTBLANK(Inc5000_Business_Analysis.xlsx!S2:S5001) -> 0
A11: id | B11: =COUNTBLANK(Inc5000_Business_Analysis.xlsx!G2:G5001) -> 0
A12: url | B12: =COUNTBLANK(Inc5000_Business_Analysis.xlsx!K2:K5001) -> 0
A13: Total company record | B13: =COUNTA(Inc5000_Business_Analysis.xlsx!J2:J5001) -> 5000
A14: Unique company | B14: =COUNTA(_xlfn.UNIQUE(Inc5000_Business_Analysis.xlsx!J2:J5001)) -> 5000

Sheet Industry Analysis
A3: Row Labels | B3: Count of company | C3: Sum of revenue | D3: Average of growth | E3: Sum of workers | H3: RANK | I3: INDUSTRY | J3: AVERAGE GROWTH
A4: Health | B4: 377 | C4: 22022876049 | D4: 637.63296 | E4: 92487 | H4: 1 | I4: Consumer Products and services | J4: 1331.791
A5: Energy | B5: 116 | C5: 21602659306 | D5: 970.03526 | E5: 23981 | H5: 2 | I5: Energy | J5: 970.035
A6: IT Services | B6: 733 | C6: 19363587015 | D6: 347.70215 | E6: 111662 | H6: 3 | I6: Food and Beverage | J6: 963.035
A7: Business Products & Services | B7: 435 | C7: 17175083779 | D7: 439.66012 | E7: 116613 | H7: 4 | I7: Health | J7: 637.632
A8: Financial Services | B8: 278 | C8: 12212242543 | D8: 572.45437 | E8: 42727 | H8: 5 | I8: Government Services | J8: 594.71
A9: Human Resources | B9: 199 | C9: 12174441948 | D9: 224.28669 | E9: 171203
A10: Logistics & Transportation | B10: 132 | C10: 11208388344 | D10: 266.17062 | E10: 29020
A11: Consumer Products & Services | B11: 230 | C11: 10746810431 | D11: 1331.7911 | E11: 24391 | H11: Rank | I11: Industry | J11: Revenue
A12: Construction | B12: 198 | C12: 10342377737 | D12: 403.42456 | E12: 23575 | H12: 1 | I12: Health | J12: 22022876049
A13: Telecommunications | B13: 135 | C13: 9336973728 | D13: 438.28913 | E13: 38391 | H13: 2 | I13: Energy | J13: 21602659306
A14: Real Estate | B14: 131 | C14: 8886571850 | D14: 576.90383 | E14: 19608 | H14: 3 | I14: IT Services | J14: 19363587015
A15: Retail | B15: 200 | C15: 8361870250 | D15: 529.52237 | E15: 33732 | H15: 4 | I15: Business Products and Services | J15: 17175083779
A16: Manufacturing | B16: 212 | C16: 7466296462 | D16: 238.49666 | E16: 33777 | H16: 5 | I16: Financial Services | J16: 12212242543
A17: Advertising & Marketing | B17: 453 | C17: 7317073720 | D17: 519.89416 | E17: 27685
A18: Software | B18: 338 | C18: 7205033140 | D18: 557.1092 | E18: 44841
A19: Food & Beverage | B19: 132 | C19: 6481046076 | D19: 963.14185 | E19: 65423
A20: Government Services | B20: 212 | C20: 6345931528 | D20: 594.71026 | E20: 28278
A21: Insurance | B21: 67 | C21: 4550304954 | D21: 243.80811 | E21: 12698
A22: Travel & Hospitality | B22: 62 | C22: 3644726185 | D22: 547.30438 | E22: 22041
A23: Security | B23: 68 | C23: 3288637477 | D23: 484.52829 | E23: 53571
A24: Engineering | B24: 66 | C24: 1341559405 | D24: 424.52157 | E24: 8098
A25: Education | B25: 78 | C25: 1181235155 | D25: 367.44415 | E25: 6203
A26: Computer Hardware | B26: 34 | C26: 1149110342 | D26: 342.11667 | E26: 1970
A27: Media | B27: 60 | C27: 1097032891 | D27: 436.9344 | E27: 8651
A28: Environmental Services | B28: 54 | C28: 789041496 | D28: 223.88 | E28: 4223
A29: Grand Total | B29: 5000 | C29: 215290911811 | D29: 516.43989 | E29: 1044849
H33: Insight No | I33: Finding | J33: Business Impact
H34: 1 | I34: Consumer Products & Services has the highest average growth (1331.8%), but it is not among the top 5 revenue-generating industries. | J34: High-growth industries are not always the largest markets; they may represent emerging opportunities rather than mature revenue leaders.
A39: Average of growth | B39: Column Labels
A40: Row Labels | B40: Enterprise | C40: Large | D40: Medium | E40: Small | F40: Grand Total | H40: Rank | I40: Industry | J40: Company Size | K40: Average Growth
A41: Advertising & Marketing | B41: 178.87097 | C41: 572.56815 | D41: 576.82291 | E41: 490.7192 | F41: 519.89416 | H41: 1 | I41: Consumer Products & Services | J41: Large | K41: 13533.198
A42: Business Products & Services | B42: 132.45313 | C42: 250.20916 | D42: 821.32118 | E42: 289.85648 | F42: 439.66012 | H42: 2 | I42: Travel & Hospitality | J42: Large | K42: 2968.9968
A43: Computer Hardware | C43: 94.6381 | D43: 197.82744 | E43: 436.35236 | F43: 342.11667 | H43: 3 | I43: Food & Beverage | J43: Medium | K43: 1902.0848
A44: Construction | B44: 88.0979 | C44: 331.98259 | D44: 275.96714 | E44: 489.17619 | F44: 403.42456 | H44: 4 | I44: Energy | J44: Small | K44: 1478.2523
A45: Consumer Products & Services | B45: 544.04914 | C45: 13533.198 | D45: 813.18224 | E45: 603.12175 | F45: 1331.7911 | H45: 5 | I45: Consumer Products & Services | J45: Medium | K45: 813.18224
A46: Education | B46: 54.3511 | C46: 512.71215 | D46: 257.45046 | E46: 426.07923 | F46: 367.44415
A47: Energy | B47: 522.79601 | C47: 803.32554 | D47: 407.32432 | E47: 1478.2523 | F47: 970.03526
A48: Engineering | B48: 166.5972 | C48: 211.28214 | D48: 192.83634 | E48: 655.47457 | F48: 424.52157
A49: Environmental Services | C49: 185.21023 | D49: 127.90318 | E49: 328.33628 | F49: 223.88
A50: Financial Services | B50: 243.02127 | C50: 272.35944 | D50: 389.83768 | E50: 778.89545 | F50: 572.45437
A51: Food & Beverage | B51: 724.40168 | C51: 432.58767 | D51: 1902.0848 | E51: 473.83628 | F51: 963.14185
A52: Government Services | B52: 615.3804 | C52: 286.9879 | D52: 361.97698 | E52: 955.78379 | F52: 594.71026
A53: Health | B53: 303.97761 | C53: 784.406 | D53: 835.00604 | E53: 484.33415 | F53: 637.63296
A54: Human Resources | B54: 142.96338 | C54: 138.67835 | D54: 196.86699 | E54: 301.90635 | F54: 224.28669
A55: Insurance | B55: 130.7649 | C55: 128.45698 | D55: 310.45468 | E55: 261.14787 | F55: 243.80811
A56: IT Services | B56: 181.01157 | C56: 159.62146 | D56: 382.22136 | E56: 369.77255 | F56: 347.70215
A57: Logistics & Transportation | B57: 156.09169 | C57: 135.21159 | D57: 146.58104 | E57: 355.28183 | F57: 266.17062
A58: Manufacturing | B58: 131.42273 | C58: 126.67029 | D58: 233.99245 | E58: 267.2371 | F58: 238.49666
A59: Media | B59: 78.941 | C59: 305.9151 | D59: 303.08883 | E59: 514.4626 | F59: 436.9344
A60: Real Estate | B60: 184.73585 | C60: 284.04077 | D60: 445.79902 | E60: 741.12279 | F60: 576.90383
A61: Retail | B61: 686.12227 | C61: 416.40263 | D61: 431.06959 | E61: 564.73944 | F61: 529.52237
... A66: Grand Total | B66: 275.85033 | C66: 706.89773 | D66: 535.02866 | E66: 497.47847 | F66: 516.43989
A71: Count of company | B71: Column Labels
A72: Row Labels | B72: Enterprise | C72: Large | D72: Medium | E72: Small | F72: Grand Total | H72: Rank | I72: Industry | J72: Company Size | K72: Avg Growth
A73: Advertising & Marketing | B73: 3 | C73: 13 | D73: 152 | E73: 285 | F73: 453 | H73: 1 | I73: Energy | J73: Small | K73: 1478.2523
A74: Business Products & Services | B74: 32 | C74: 39 | D74: 135 | E74: 229 | F74: 435 | H74: 2 | I74: Government Services | J74: Small | K74: 955.78379
A75: Computer Hardware | C75: 1 | D75: 12 | E75: 21 | F75: 34 | H75: 3 | I75: Health | J75: Medium | K75: 835.00604
A76: Construction | B76: 4 | C76: 11 | D76: 64 | E76: 119 | F76: 198 | H76: 4 | I76: Consumer Products & Services | J76: Medium | K76: 813.18224
A77: Consumer Products & Services | B77: 10 | C77: 12 | D77: 62 | E77: 146 | F77: 230 | H77: 5 | I77: Financial Services | J77: Small | K77: 778.89545
A78: Education | B78: 1 | C78: 6 | D78: 28 | E78: 43 | F78: 78
A79: Energy | B79: 11 | C79: 21 | D79: 32 | E79: 52 | F79: 116
A80: Engineering | B80: 4 | C80: 7 | D80: 22 | E80: 33 | F80: 66
A81: Environmental Services | C81: 3 | D81: 26 | E81: 25 | F81: 54
A82: Financial Services | B82: 20 | C82: 33 | D82: 77 | E82: 148 | F82: 278
A83: Food & Beverage | B83: 21 | C83: 16 | D83: 42 | E83: 53 | F83: 132
A84: Government Services | B84: 12 | C84: 24 | D84: 95 | E84: 81 | F84: 212
A85: Health | B85: 38 | C85: 53 | D85: 139 | E85: 147 | F85: 377
A86: Human Resources | B86: 37 | C86: 29 | D86: 46 | E86: 87 | F86: 199
A87: Insurance | B87: 4 | C87: 13 | D87: 22 | E87: 28 | F87: 67
A88: IT Services | B88: 29 | C88: 69 | D88: 305 | E88: 330 | F88: 733
A89: Logistics & Transportation | B89: 10 | C89: 15 | D89: 31 | E89: 76 | F89: 132
A90: Manufacturing | B90: 10 | C90: 15 | D90: 79 | E90: 108 | F90: 212
A91: Media | B91: 1 | C91: 4 | D91: 16 | E91: 39 | F91: 60
A92: Real Estate | B92: 11 | C92: 13 | D92: 32 | E92: 75 | F92: 131
A93: Retail | B93: 9 | C93: 17 | D93: 42 | E93: 132 | F93: 200
... A98: Grand Total | B98: 312 | C98: 484 | D98: 1667 | E98: 2537 | F98: 5000
A101: Average of growth | B101: Column Labels
A102: Row Labels | B102: AK | C102: AL | D102: AR | E102: AZ | F102: CA | G102: CO | H102: CT | I102: DC | J102: DE | K102: FL | L102: GA | M102: HI | N102: IA | O102: ID | P102: IL | Q102: IN | R102: KS | S102: KY | T102: LA | U102: MA | V102: MD | W102: ME | X102: MI | Y102: MN | Z102: MO | AA102: MS | AB102: MT | AC102: NC | AD102: ND | AE102: NE | AF102: NH | AG102: NJ | AH102: NM | AI102: NV | AJ102: NY | AK102: OH | AL102: OK | AM102: OR | AN102: PA | AO102: PR | AP102: RI | AQ102: SC | AR102: SD | AS102: TN | AT102: TX | AU102: UT | AV102: VA | AW102: VT | AX102: WA | AY102: WI | AZ102: WV | BA102: Grand Total
A103: Advertising & Marketing | B103: 67.5724 | D103: 809.9576 | E103: 813.29718 | F103: 484.87529 | G103: 453.67786 | H103: 115.6016 | I103: 1664.4145 | K103: 671.62094 | L103: 347.56513 | N103: 68.8154 | O103: 483.3171 | P103: 184.49687 | Q103: 246.32725 | R103: 949.5891 | T103: 198.37802 | U103: 695.69313 | V103: 203.65511 | W103: 190.9974 | X103: 143.84245 | Y103: 222.67873 | Z103: 1030.0925 | AC103: 299.34755 | AD103: 78.672 | AE103: 61.335133 | AF103: 139.041 | AG103: 578.88943 | AI103: 494.9058 | AJ103: 793.62563 | AK103: 456.39312 | AL103: 108.62735 | AM103: 369.85001 | AN103: 481.60789 | AP103: 65.7443 | AQ103: 890.0261 | AR103: 409.9096 | AS103: 134.4918 | AT103: 766.24906 | AU103: 638.29657 | AV103: 255.03344 | AX103: 563.91698 | AY103: 258.704 | BA103: 519.89416
A104: Business Products & Services | C104: 143.19785 | E104: 257.6072 | F104: 196.02785 | G104: 401.17305 | H104: 146.99996 | I104: 131.6053 | J104: 83.3738 | K104: 388.84143 | L104: 245.40478 | N104: 121.37227 | P104: 359.77759 | Q104: 1547.8621 | R104: 3593.8158 | S104: 81.729267 | T104: 94.3718 | U104: 184.61711 | V104: 175.77758 | W104: 572.9642 | X104: 100.96425 | Y104: 385.00502 | Z104: 334.16988 | AC104: 468.16096 | AE104: 62.9204 | AF104: 1300.0487 | AG104: 115.73348 | AI104: 160.31694 | AJ104: 427.93245 | AK104: 123.84558 | AL104: 160.03423 | AM104: 80.0775 | AN104: 227.36814 | AO104: 183.5322 | AP104: 159.17025 | AQ104: 380.69632 | AS104: 219.37287 | AT104: 297.97235 | AU104: 212.88441 | AV104: 2848.5468 | AW104: 50.2924 | AX104: 178.21954 | AY104: 225.038 | BA104: 439.66012
A105: Computer Hardware | E105: 174.8746 | F105: 134.30995 | K105: 87.592425 | L105: 128.3503 | P105: 149.5773 | U105: 79.2873 | Y105: 291.9094 | AG105: 49.3573 | AJ105: 148.1659 | AK105: 359.21495 | AN105: 182.9767 | AS105: 46.6564 | AV105: 3532.3775 | AX105: 75.00575 | AY105: 1778.5396 | BA105: 342.11667
A106: Construction | C106: 91.29985 | E106: 419.75952 | F106: 422.88994 | G106: 106.4554 | H106: 73.5064 | I106: 48.5233 | J106: 519.7045 | K106: 364.85744 | L106: 233.22352 | N106: 424.6077 | O106: 289.8572 | P106: 344.34094 | Q106: 387.5037 | R106: 103.4652 | T106: 1987.7203 | U106: 140.23903 | V106: 288.02078 | W106: 418.995 | X106: 125.5716 | Y106: 293.86824 | Z106: 408.1102 | AA106: 2117.7132 | AC106: 627.43756 | AD106: 148.0427 | AG106: 286.17023 | AH106: 887.2925 | AJ106: 237.83402 | AK106: 100.105 | AL106: 378.1504 | AM106: 164.2346 | AN106: 952.27252 | AP106: 46.4731 | AQ106: 102.96577 | AS106: 309.72026 | AT106: 571.07421 | AU106: 517.13215 | AV106: 190.11814 | AX106: 281.00245 | AY106: 104.124 | BA106: 403.42456
A107: Consumer Products & Services | C107: 534.76558 | D107: 226.6225 | E107: 145.79915 | F107: 4330.1089 | G107: 1981.9385 | H107: 43.6364 | J107: 372.9326 | K107: 634.39357 | L107: 334.5606 | N107: 64.8757 | P107: 353.48124 | Q107: 327.4741 | S107: 486.97245 | T107: 115.7254 | U107: 256.99863 | V107: 2120.9417 | X107: 90.3792 | Y107: 61.0213 | Z107: 315.71058 | AB107: 54.0574 | AC107: 80.3973 | AE107: 199.51335 | AG107: 481.25518 | AH107: 790.275 | AI107: 218.6656 | AJ107: 1323.2947 | AK107: 276.04214 | AM107: 1027.5356 | AN107: 1540.4949 | AQ107: 777.0706 | AS107: 212.5057 | AT107: 235.83715 | AU107: 882.95138 | AV107: 194.46345 | AX107: 144.74257 | AY107: 315.3846 | BA107: 1331.7911
A108: Education | C108: 258.3444 | E108: 120.3061 | F108: 694.3222 | G108: 524.7026 | H108: 244.65015 | J108: 49.5919 | K108: 82.199367 | P108: 613.32468 | Q108: 1423.3754 | R108: 54.3511 | U108: 803.14775 | V108: 180.4377 | X108: 171.76793 | Z108: 95.1345 | AC108: 122.5666 | AG108: 104.087 | AJ108: 284.03349 | AK108: 169.45425 | AM108: 179.4927 | AN108: 140.79114 | AP108: 43.8377 | AQ108: 219.2895 | AT108: 158.12922 | AU108: 644.39677 | AV108: 261.5087 | AX108: 97.69815 | BA108: 367.44415
A109: Energy | C109: 311.3011 | D109: 157.86355 | F109: 1150.9525 | G109: 664.2309 | H109: 553.0519 | I109: 664.84327 | K109: 98.3003 | L109: 1625.5632 | M109: 693.34285 | N109: 6020.9548 | Q109: 53.3651 | T109: 447.9153 | U109: 1097.2147 | W109: 19876.517 | X109: 169.3865 | Y109: 160.4142 | AB109: 297.0451 | AC109: 5467.5586 | AG109: 824.0932 | AJ109: 969.88692 | AK109: 394.27973 | AL109: 101.07075 | AN109: 126.76347 | AP109: 2382.5638 | AS109: 86.5446 | AT109: 325.92927 | AV109: 733.9883 | AX109: 804.61905 | AY109: 329.05135 | BA109: 970.03526
A110: Engineering | C110: 2930.8583 | E110: 423.9347 | F110: 207.90785 | G110: 84.4393 | H110: 112.1183 | K110: 297.81943 | P110: 378.6636 | R110: 105.2559 | T110: 265.14613 | U110: 196.18394 | V110: 149.1017 | Y110: 579.1398 | Z110: 279.7388 | AG110: 156.47453 | AI110: 64.2124 | AJ110: 97.4332 | AK110: 106.6128 | AL110: 1603.5675 | AN110: 224.43961 | AT110: 543.01167 | AV110: 192.7116 | AX110: 325.224 | AY110: 218.8931 | BA110: 424.52157
A111: Environmental Services | E111: 192.37215 | F111: 239.17017 | G111: 115.2594 | H111: 46.5121 | J111: 98.7383 | K111: 226.8116 | P111: 238.4592 | R111: 64.5109 | T111: 108.99595 | U111: 94.5316 | Y111: 286.838 | Z111: 688.5959 | AC111: 102.4137 | AF111: 73.4837 | AG111: 83.114633 | AJ111: 142.46 | AK111: 122.82395 | AL111: 189.30743 | AN111: 419.70963 | AT111: 327.61862 | AV111: 66.26585 | AY111: 58.8284 | BA111: 223.88
A112: Financial Services | C112: 78.8347 | E112: 3782.8067 | F112: 562.87387 | G112: 417.49276 | H112: 274.5655 | J112: 488.604 | K112: 356.44328 | L112: 304.10985 | N112: 44.2462 | O112: 68.3756 | P112: 565.10903 | Q112: 1331.7808 | R112: 287.62407 | S112: 128.2374 | T112: 358.0403 | U112: 146.2032 | V112: 116.3885 | W112: 231.4406 | X112: 666.4222 | Y112: 730.96156 | Z112: 166.91957 | AA112: 143.03053 | AB112: 1373.7533 | AC112: 113.34662 | AE112: 109.03985 | AF112: 194.3223 | AG112: 940.80398 | AI112: 178.3813 | AJ112: 311.07364 | AK112: 146.55101 | AL112: 510.0435 | AM112: 1318.7688 | AN112: 903.99588 | AQ112: 524.4268 | AR112: 80.1609 | AS112: 156.66302 | AT112: 974.07801 | AU112: 273.0028 | AV112: 213.59824 | AX112: 187.22754 | AY112: 60.3896 | BA112: 572.45437
A113: Food & Beverage | C113: 368.2486 | E113: 87.5235 | F113: 2654.47 | G113: 246.68615 | H113: 575.30225 | J113: 1136.8085 | K113: 343.82057 | L113: 242.384 | P113: 486.00818 | Q113: 362.2909 | R113: 322.06225 | S113: 153.5098 | U113: 178.0874 | V113: 147.8917 | W113: 69.9527 | X113: 227.78177 | Y113: 218.3826 | Z113: 120.0998 | AC113: 6383.6592 | AF113: 78.2826 | AG113: 1416.4588 | AI113: 48.1823 | AJ113: 316.04237 | AK113: 108.2538 | AL113: 652.9412 | AM113: 139.9576 | AN113: 88.1988 | AP113: 107.6325 | AS113: 188.5047 | AT113: 394.54552 | AU113: 247.5057 | AV113: 2948.1458 | AX113: 279.58952 | AY113: 98.758733 | BA113: 963.14185
A114: Government Services | C114: 822.71211 | D114: 92.79645 | E114: 128.83615 | F114: 232.7882 | G114: 112.66276 | I114: 605.22481 | K114: 520.84905 | L114: 969.79813 | M114: 65.3897 | N114: 964.3957 | P114: 530.9633 | R114: 870.44655 | T114: 2358.6178 | U114: 238.59675 | V114: 351.38226 | X114: 474.5385 | AE114: 352.2158 | AF114: 619.8047 | AG114: 774.66365 | AH114: 576.6209 | AJ114: 142.1284 | AK114: 467.0294 | AL114: 222.2353 | AN114: 49.8663 | AQ114: 108.05955 | AS114: 760.2982 | AT114: 372.36795 | AU114: 719.42147 | AV114: 677.6666 | AY114: 71.5245 | AZ114: 730.3076 | BA114: 594.71026
A115: Health | C115: 492.67422 | E115: 1833.7521 | F115: 836.55654 | G115: 232.15534 | H115: 458.8745 | I115: 594.0254 | J115: 134.5826 | K115: 2215.7202 | L115: 234.13161 | M115: 12127.913 | N115: 129.7407 | O115: 140.91805 | P115: 498.93308 | Q115: 142.28425 | R115: 637.21343 | S115: 118.8333 | U115: 196.71475 | V115: 243.22961 | W115: 227.777 | X115: 95.3343 | Y115: 260.4643 | Z115: 119.39627 | AA115: 261.64295 | AC115: 175.84168 | AD115: 97.86735 | AE115: 211.4236 | AF115: 88.3694 | AG115: 157.32088 | AI115: 528.4433 | AJ115: 466.96346 | AK115: 561.53274 | AM115: 101.9166 | AN115: 261.66021 | AP115: 274.4945 | AQ115: 198.77523 | AS115: 627.41758 | AT115: 240.72534 | AU115: 1665.3052 | AV115: 882.46127 | AX115: 365.90559 | AY115: 3122.3631 | BA115: 637.63296
A116: Human Resources | C116: 65.3526 | E116: 310.84063 | F116: 221.80694 | G116: 309.0117 | I116: 287.431 | J116: 140.5585 | K116: 232.30901 | L116: 215.3631 | O116: 3277.519 | P116: 93.863267 | Q116: 229.55992 | S116: 190.3493 | T116: 77.5557 | U116: 267.1105 | V116: 594.70743 | X116: 170.7455 | Y116: 274.9688 | Z116: 321.8937 | AC116: 139.42978 | AE116: 109.0234 | AF116: 121.1214 | AG116: 128.94869 | AJ116: 240.52648 | AK116: 130.92633 | AL116: 160.5288 | AN116: 180.01048 | AP116: 109.6763 | AQ116: 64.9684 | AS116: 123.55561 | AT116: 326.66732 | AU116: 453.5641 | AV116: 86.468967 | AX116: 90.636633 | AY116: 181.4145 | BA116: 224.28669
A117: Insurance | F117: 185.24786 | H117: 222.1629 | K117: 137.09581 | L117: 178.6205 | N117: 83.6846 | P117: 952.42922 | Q117: 61.2205 | U117: 389.8158 | W117: 78.5727 | Y117: 202.18575 | AA117: 98.2155 | AC117: 81.46905 | AE117: 461.1983 | AG117: 158.56336 | AI117: 169.7101 | AJ117: 110.08297 | AK117: 1108.1723 | AM117: 131.1261 | AN117: 110.7915 | AQ117: 132.4395 | AS117: 286.4851 | AT117: 69.40728 | AU117: 378.1672 | AV117: 538.84235 | AX117: 89.603 | AY117: 144.4673 | BA117: 243.80811
A118: IT Services | C118: 126.29515 | D118: 56.9499 | E118: 372.29495 | F118: 303.3188 | G118: 284.73123 | H118: 96.369517 | I118: 967.5885 | J118: 706.27907 | K118: 463.9774 | L118: 262.13813 | N118: 122.11678 | O118: 185.7292 | P118: 256.78856 | Q118: 191.52059 | R118: 411.33188 | S118: 168.54273 | T118: 183.87834 | U118: 231.30496 | V118: 478.6816 | W118: 155.2431 | X118: 542.09454 | Y118: 217.00228 | Z118: 526.78551 | AA118: 151.7349 | AC118: 208.40329 | AE118: 85.94635 | AF118: 96.774533 | AG118: 567.07661 | AH118: 166.6374 | AI118: 102.91187 | AJ118: 323.72518 | AK118: 179.08911 | AL118: 1514.437 | AM118: 150.59911 | AN118: 208.281 | AP118: 131.494 | AQ118: 221.66073 | AS118: 393.91432 | AT118: 607.44977 | AU118: 797.3745 | AV118: 296.59734 | AW118: 59.3865 | AX118: 438.36768 | AY118: 123.75686 | BA118: 347.70215
A119: Logistics & Transportation | C119: 467.9046 | E119: 71.9631 | F119: 298.67478 | H119: 115.4856 | J119: 75.0694 | K119: 198.97741 | L119: 71.2754 | N119: 42.5457 | P119: 183.77571 | Q119: 191.40372 | R119: 111.8666 | S119: 954.6334 | T119: 123.2996 | U119: 393.5302 | V119: 110.3954 | X119: 874.49885 | Y119: 198.2543 | Z119: 371.31077 | AA119: 72.719 | AC119: 307.16428 | AF119: 88.3001 | AG119: 685.62739 | AJ119: 271.45335 | AK119: 301.26812 | AN119: 136.2757 | AQ119: 380.7932 | AT119: 145.79291 | AU119: 175.50695 | AV119: 95.4431 | AX119: 158.2643 | AY119: 88.24025 | BA119: 266.17062
A120: Manufacturing | C120: 237.48335 | D120: 177.6602 | E120: 395.52776 | F120: 488.53425 | G120: 61.88875 | H120: 81.6686 | K120: 184.15612 | L120: 95.898364 | N120: 305.2213 | P120: 582.24765 | Q120: 124.749 | R120: 77.1581 | S120: 112.8542 | T120: 158.5369 | U120: 47.9127 | X120: 138.4425 | Y120: 107.15834 | Z120: 93.350875 | AA120: 832.2485 | AC120: 127.26283 | AE120: 161.57655 | AG120: 112.50177 | AI120: 107.0527 | AJ120: 235.33152 | AK120: 87.133714 | AL120: 87.303125 | AM120: 123.11187 | AN120: 211.55101 | AQ120: 102.53015 | AS120: 167.18787 | AT120: 271.03983 | AU120: 166.20699 | AV120: 500.55473 | AX120: 115.55675 | AY120: 164.15681 | BA120: 238.49666
A121: Media | C121: 147.54477 | F121: 835.66755 | K121: 363.8727 | L121: 234.9164 | P121: 223.5506 | Q121: 108.1764 | T121: 596.389 | U121: 274.8867 | W121: 83.1974 | Y121: 141.424 | AC121: 397.20845 | AG121: 269.781 | AJ121: 474.79141 | AK121: 417.93907 | AN121: 59.99125 | AQ121: 87.6674 | AS121: 88.2451 | AT121: 218.2437 | AV121: 308.64635 | AX121: 81.663 | AY121: 378.3562 | BA121: 436.9344
A122: Real Estate | C122: 1865.5423 | D122: 85.4256 | E122: 656.65417 | F122: 512.85842 | G122: 453.97597 | I122: 977.87773 | K122: 320.43346 | L122: 618.12852 | M122: 265.0319 | P122: 635.60957 | Q122: 1352.351 | R122: 208.1257 | T122: 625.002 | U122: 123.93285 | V122: 179.975 | X122: 2172.0412 | Y122: 274.721 | Z122: 2091.189 | AC122: 531.6326 | AF122: 189.8205 | AI122: 75.6385 | AJ122: 345.13199 | AK122: 1366.9589 | AL122: 726.2162 | AM122: 123.28683 | AN122: 587.03773 | AP122: 47.4501 | AQ122: 504.9494 | AS122: 224.91633 | AT122: 180.08242 | AU122: 1048.3781 | AV122: 438.16803 | AX122: 1174.4444 | AY122: 238.2334 | BA122: 576.90383
A123: Retail | C123: 612.5239 | E123: 172.76923 | F123: 932.18376 | G123: 297.47093 | H123: 245.64503 | J123: 1049.7842 | K123: 710.67707 | L123: 286.19686 | N123: 76.84225 | O123: 347.10727 | P123: 460.05924 | Q123: 115.1667 | R123: 354.6177 | S123: 81.4806 | T123: 54.6073 | U123: 200.43072 | V123: 49.506 | W123: 320.3488 | X123: 371.44835 | Y123: 214.33949 | Z123: 137.2682 | AC123: 447.73292 | AD123: 221.557 | AE123: 130.31637 | AG123: 143.18331 | AI123: 632.22495 | AJ123: 743.43616 | AK123: 340.45555 | AL123: 97.434 | AM123: 1033.0512 | AN123: 495.52758 | AP123: 5220.9165 | AQ123: 323.46805 | AS123: 190.40647 | AT123: 425.52581 | AU123: 272.15016 | AV123: 1074.0749 | AX123: 470.1529 | AY123: 971.35227 | AZ123: 64.1135 | BA123: 529.52237
...

Sheet Company Size Analysis
A3: Row Labels | B3: Count of company
A4: Enterprise | B4: 312
A5: Large | B5: 484
A6: Medium | B6: 1667
A7: Small | B7: 2537
A8: Grand Total | B8: 5000
B12: Company Size | C12: Median Growth
B13: Enterprise | C13: {=MEDIAN(_xlfn._xlws.FILTER('Clean Data'!$P$2:$P$5001,'Clean Data'!$T$2:$T$5001=F4))} -> 151.7228
B14: Large | C14: {=MEDIAN(_xlfn._xlws.FILTER('Clean Data'!$P$2:$P$5001,'Clean Data'!$H$2:$H$5001=F5))} -> 110.1436
B15: Medium | C15: {=MEDIAN(_xlfn._xlws.FILTER('Clean Data'!$P$2:$P$5001,'Clean Data'!$H$2:$H$5001=F6))} -> 110.1436
B16: Small | C16: {=MEDIAN(_xlfn._xlws.FILTER('Clean Data'!$P$2:$P$5001,'Clean Data'!$H$2:$H$5001=F7))} -> 110.1436
B19: INSIGHT | C19: Large companies have the highest average growth in the dataset, but the substantially lower median growth indicates that this result is strongly influenced by a small number of extreme high-growth companies

Sheet Geographical Analysis
A3: Row Labels | B3: Count of company | C3: Sum of revenue | D3: Average of growth | E3: Average Revenue per Company
A4: Tennessee | B4: 80 | C4: 8153943024 | D4: 267.61047 | E4: 1.0192429e+08
A5: Wisconsin | B5: 70 | C5: 7063487004 | D5: 442.69816 | E5: 1.0090696e+08 | H5: Rank | I5: State | J5: No of Companies | M5: Rank | N5: State | O5: Avg Growth(MIN 50 Companies)
A6: Texas | B6: 404 | C6: 27263931736 | D6: 440.92521 | E6: 67484980 | H6: 1 | I6: California | J6: 694 | M6: 1 | N6: California | O6: 876.19916
A7: Minnesota | B7: 94 | C7: 6085563921 | D7: 267.687 | E7: 64740042 | H7: 2 | I7: Texas | J7: 404 | M7: 2 | N7: Arizona | O7: 778.15829
A8: Ohio | B8: 171 | C8: 11051298826 | D8: 314.35538 | E8: 64627479 | H8: 3 | I8: New York | J8: 335 | M8: 3 | N8: Virginia | O8: 674.52999
A9: Michigan | B9: 130 | C9: 7687537169 | D9: 367.55038 | E9: 59134901 | H9: 4 | I9: Florida | J9: 303 | M9: 4 | N9: Oregon | O9: 655.851
A10: Illinois | B10: 238 | C10: 13548067258 | D10: 371.03295 | E10: 56924652 | H10: 5 | I10: Virginia | J10: 284 | M10: 5 | N10: Alambama | O10: 648.14198
A11: Indiana | B11: 73 | C11: 3766357059 | D11: 444.65107 | E11: 51593932
A12: Arizona | B12: 104 | C12: 4782485805 | D12: 778.15829 | E12: 45985440
A13: California | B13: 694 | C13: 31017385250 | D13: 876.19916 | E13: 44693639
A14: Massachusetts | B14: 174 | C14: 7714875801 | D14: 497.09161 | E14: 44338367 | H14: Rank | I14: State | J14: Average of Growth | M14: Rank | N14: State | O14: No of Companies | P14: Avg Revenue of companies
A15: Colorado | B15: 122 | C15: 5285063747 | D15: 448.49266 | E15: 43320195 | H15: 1 | I15: Hawaii | J15: 2769.0041 | M15: 1 | N15: Tennessee | O15: 80 | P15: 1.0192429e+08
A16: North Carolina | B16: 146 | C16: 5287506108 | D16: 475.1414 | E16: 36215795 | H16: 2 | I16: Maine | J16: 1694.7104 | M16: 2 | N16: Wisconsin | O16: 70 | P16: 1.0090696e+08
A17: Utah | B17: 86 | C17: 3030554373 | D17: 561.86936 | E17: 35239004 | H17: 3 | I17: California | J17: 876.19916 | M17: 3 | N17: Texas | O17: 404 | P17: 67484980
A18: New Jersey | B18: 164 | C18: 5695140251 | D18: 403.7072 | E18: 34726465 | H18: 4 | I18: New Mexico | J18: 817.8129 | M18: 4 | N18: Minnesota | O18: 94 | P18: 64740042
A19: New York | B19: 335 | C19: 11289216207 | D19: 489.09057 | E19: 33699153 | H19: 5 | I19: Arizona | J19: 778.15829 | M19: 5 | N19: Ohio | O19: 171 | P19: 64627479
A20: Virginia | B20: 284 | C20: 9475062257 | D20: 674.52999 | E20: 33362895
A21: Georgia | B21: 209 | C21: 6247240672 | D21: 280.79995 | E21: 29891104
A22: Florida | B22: 303 | C22: 9012608940 | D22: 567.55941 | E22: 29744584
A23: Missouri | B23: 72 | C23: 2120454513 | D23: 427.40732 | E23: 29450757
A24: Oregon | B24: 61 | C24: 1762495329 | D24: 655.85178 | E24: 28893366
A25: Pennsylvania | B25: 191 | C25: 5069151677 | D25: 375.4008 | E25: 26540061
A26: South Carolina | B26: 55 | C26: 1440588332 | D26: 308.49417 | E26: 26192515
A27: Maryland | B27: 121 | C27: 2748758987 | D27: 375.85813 | E27: 22717016
A28: Alabama | B28: 56 | C28: 1226129111 | D28: 648.14198 | E28: 21895163
A29: Washington | B29: 107 | C29: 1982437206 | D29: 336.53206 | E29: 18527451
A30: Grand Total | B30: 4544 | C30: 199807340563 | D30: 518.35787 | E30: 43971686

Sheet Key Findings
B1: Business Question | C1: Finding | D1: Evidence | E1: Implication
A2: 1 | B2: Which industries grow fastest? | C2: High growth and high revenue scale do not necessarily occur in the same industries. Consumer Products & Services has the highest average growth, while Health leads in total revenue. | D2: Consumer Products & Services: 1,331.79% average growth. Health: $2.203B total revenue and 637.63% average growth. | E2: Businesses evaluating expansion opportunities should distinguish between emerging high-growth segments and established high-revenue segments rather than using growth alone as the decision criterion.
A3: 2 | B3: Does company size relate to growth? | C3: Large companies have the highest average growth, but the difference between average and median growth indicates that extreme observations strongly influence the averages. | D3: Large companies: 706.90% average growth vs 110.14% median growth. Enterprise companies: 275.85% average vs 151.72% median. | E3: Growth comparisons should consider both average and median values to avoid making decisions based on unusually high-growth companies.
A4: 3 | B4: Where are high-growth companies concentrated? | C4: California combines the largest concentration of companies with the highest average growth among states containing at least 50 companies. | D4: California has 694 companies and 876.20% average growth. Arizona ranks second with 104 companies and 778.16% average growth. | E4: California represents a strong combination of market scale and growth, while smaller states should be evaluated cautiously because their averages can be affected by small sample sizes.
A5: 4 | B5: Which states have the highest average revenue per company? | C5: States with the largest number of companies are not necessarily the states with the highest average revenue per company. | D5: Tennessee: $101.92M average revenue/company with 80 companies. Wisconsin: $100.91M with 70 companies. Texas: $67.48M with 404 companies. | E5: Market attractiveness should be evaluated using both company concentration and revenue efficiency rather than company count alone.
A6: 5 | B6: How representative is the average growth rate? | C6: The overall growth distribution is highly skewed, with extreme-growth companies substantially increasing the average growth rate. | D6: Median growth is 151.72% versus average growth of 516.44%. 82.14% of companies have growth of 500% or less, while only 17.86% exceed 500%. | E6: Median growth should be considered alongside average growth when evaluating typical company performance, as the average alone may overstate the experience of most companies.
A7: 6 | B7: What factors are associated with revenue? | C7: Revenue has a weak positive relationship with workforce size and a very weak relationship with years on the list, while growth has virtually no linear relationship with revenue. | D7: Revenue vs Workers correlation: 0.266; Revenue vs Years on List: 0.151; Revenue vs Growth: 0.002. | E7: Revenue should not be predicted from growth rate alone. Workforce size shows a somewhat stronger association with revenue, but other business factors likely explain much of the variation.
A8: 7 | B8: How concentrated is company growth? | C8: Most companies have moderate growth, while a smaller group of companies records exceptionally high growth. This indicates that the overall average growth is influenced by a relatively small number of high-growth companies. | D8: 1,646 companies (32.92%) have growth ≤100%, while 2,461 companies (49.22%) fall between 100% and 500%. Only 424 companies (8.48%) are between 500% and 1,000%, and 469 companies (9.38%) exceed 1,000%. Therefore, 82.14% of companies have growth below 500%, while only 17.86% exceed 500%. | E8: Management should use median growth and growth distribution alongside average growth when evaluating business performance, because the average can be disproportionately affected by a smaller number of extremely high-growth companies.

Sheet Growth Analysis
A1: Growth Band | B1: Company Count | C1: % of Companies
A2: ≤100% | B2: =COUNTIF('Clean Data'!$P$2:$P$5001,"<=100") -> 1646 | C2: =B2/$B$6 -> 0.3292
A3: 100–500% | B3: =COUNTIFS('Clean Data'!$P$2:$P$5001,">100",'Clean Data'!$P$2:$P$5001,"<=500") -> 2461 | C3: =B3/$B$6 -> 0.4922
A4: 500–1,000% | B4: =COUNTIFS('Clean Data'!$P$2:$P$5001,">500",'Clean Data'!$P$2:$P$5001,"<=1000") -> 424 | C4: =B4/$B$6 -> 0.0848
A5: >1,000% | B5: =COUNTIF('Clean Data'!$P$2:$P$5001,">1000") -> 469 | C5: =B5/$B$6 -> 0.0938
A6: Total | B6: =SUM(B2:B5) -> 5000 | C6: =SUM(C2:C5) -> 1
A8: Overall Median Growth | B8: =MEDIAN('Clean Data'!$P$2:$P$5001) -> 151.7228
A9: Overall Average Growth | B9: =AVERAGE('Clean Data'!$P$2:$P$5001) -> 516.43989
A11: =SUM(C4:C5) -> 0.1786
A13: INSIGHT | B13: Most companies (82.1%) have growth below 500%, while 17.9% exceed 500%, indicating that the very high overall average growth is influenced by a smaller group of high-growth companies.

Sheet Relationship Analysis
A1: Relationship | B1: Correlation | C1: Interpretation
A2: Revenue vs Workers | B2: =CORREL('Clean Data'!$Q$2:$Q$5001,'Clean Data'!$H$2:$H$5001) -> 0.26569902 | C2: Weak-to-moderate positive relationship
A3: Revenue vs Growth | B3: =CORREL('Clean Data'!$Q$2:$Q$5001,'Clean Data'!$P$2:$P$5001) -> 0.0017154375 | C3: Essentially no linear relationship
A4: Revenue vs Years on List | B4: =CORREL('Clean Data'!$Q$2:$Q$5001,'Clean Data'!$S$2:$S$5001) -> 0.15052295 | C4: Very weak positive relationship

Sheet Dashboard
A1: Inc. 5000 Business Performance Dashboard
A3: Total Companies | D3: Total Revenue | G3: Average Growth | J3: Median Growth | M3: Average Workers
A4: =COUNTA('Clean Data'!$J$2:$J$5001) -> 5000 | D4: =SUM('Clean Data'!$Q$2:$Q$5001) -> 215290911811 | G4: =AVERAGE('Clean Data'!$P$2:$P$5001) -> 516.43989 | J4: =MEDIAN('Clean Data'!$P$2:$P$5001) -> 151.7228 | M4: =AVERAGE('Clean Data'!$H$2:$H$5001) -> 208.9698

Sheet SQL Insights
A1: Analysis | B1: Business Question | C1: Key Finding | D1: Business Implication
A2: Industry Performance | B2: Which industries combine revenue scale, company presence and growth? | C2: Health leads total revenue, while Energy has nearly similar revenue with much higher average growth. | D2: Evaluate industries using both scale and growth.
A3: Company Size Performance | B3: Does company size relate to revenue and growth? | C3: Enterprise companies generate the most revenue, while Large companies have the highest average growth. | D3: Revenue scale and growth should be evaluated separately
A4: Geographic Opportunity | B4: Which states combine company concentration, revenue scale and growth? | C4: California combines the highest company concentration and total revenue with very high average growth. | D4: Evaluate geographic opportunities using both scale and growth.
A5: Growth Segmentation | B5: How is company growth distributed? | C5: 82.14% of companies have growth ≤500%, while 17.86% exceed 500%. | D5: Use median and distribution alongside average growth.
A6: High Revenue + High Growth | B6: Which companies combine substantial revenue scale with rapid growth? | C6: Only one company meets the $1B revenue and 500% growth thresholds. | D6: Companies achieving both substantial scale and extreme growth are uncommon.
A7: Company Ranking by Industry | B7: Which companies are the leading revenue performers within their respective industries? | C7: SQL ranking identified the top 3 revenue companies within each of the 25 industries. | D7: Industry-specific benchmarking can identify leading companies without comparing firms across fundamentally different markets.
A8: Growth Leaders Within Industry | B8: Which companies are the highest-growth performers within their respective industries? | C8: SQL ranking identifies the top 3 growth companies within each industry, enabling industry-specific benchmarking. | D8: Growth leaders should be compared against their industry peers rather than only against the overall market.
A9: Industry × Company Size | B9: Which industry and company-size combinations show the strongest growth? | C9: Growth varies substantially across industry-size combinations, with Energy–Small companies showing the highest average growth among combinations with at least 50 companies | D9: Company size should not be evaluated independently of industry when assessing growth performance.
A10: Industry Opportunity Scorecard | B10: Which industries combine strong growth, revenue scale, and sufficient market presence? | C10: Industries can be segmented into opportunity categories by evaluating average growth, total revenue, and company count together rather than relying on a single metric. | D10: Businesses can prioritize industries that demonstrate both market scale and growth potential, while avoiding decisions based solely on high growth or high revenue.
A11: Industry Opportunity Scorecard | B11: Which industries combine strong growth, revenue scale, and sufficient market presence? | C11: Consumer Products & Services and Energy are classified as High Opportunity, combining strong average growth with substantial revenue and company presence. Consumer Products & Services shows 1,331.79% average growth, while Energy shows 970.04%. | D11: Industries should be prioritized using a combination of growth, revenue scale, and market presence, rather than relying on a single performance metric.
